Workbook
Name Slicer_Product: #N/A
Name Slicer_region: #N/A

Sheet Product_Master
A1: SKU_ID | B1: Product_Name | C1: Category | D1: Sub_Category | E1: UOM | F1: Unit_Cost_(INR) | G1: Selling_Price_(INR) | H1: Lead_Time_(Days) | I1: Min_Order_Qty | J1: Shelf_Life_(Days) | K1: Storage_Type | L1: Status | M1: Holding cost | N1: Ordering cost | O1: Annual demand | P1: EOQ | Q1: Std_Dev | R1: Safety Stock | S1: Reorder Point | T1: Days Of Cover
A2: SKU001 | B2: Surf Excel 1kg | C2: Detergent | D2: Laundry | E2: Units | F2: 85 | G2: 120 | H2: 14 | I2: 500 | J2: 730 | K2: Ambient | L2: Active | M2: =0.2*F2 -> 17 | N2: 500 | O2: =SUMIFS(Demand_Data!H2:H1081,Demand_Data!B2:B1081,Table2[[#This Row],[SKU_ID]],Demand_Data!F2:F1081,2024) -> 145273 | P2: =((2*Table2[[#This Row],[Annual demand]]*Table2[[#This Row],[Ordering cost]])/Table2[[#This Row],[Holding cost]])^(1/2) -> 2923.2637 | Q2: =STDEV(Demand_Data!B2:B1081,Table2[[#This Row],[SKU_ID]],Demand_Data!H2:H1081) -> 3433.0961 | R2: =1.65*Table2[[#This Row],[Std_Dev]]*(Table2[[#This Row],[Lead_Time_(Days)]]/30)^1/2 -> 1321.742 | S2: =((Table2[[#This Row],[Annual demand]]/365)*Table2[[#This Row],[Lead_Time_(Days)]])+Table2[[#This Row],[Safety Stock]] -> 6893.8571 | T2: =Table3[[#This Row],[Closing_Stock]]/(Table2[[#This Row],[Annual demand]]/365) -> 8.7762007
A3: SKU002 | B3: Surf Excel 500g | C3: Detergent | D3: Laundry | E3: Units | F3: 45 | G3: 68 | H3: 14 | I3: 1000 | J3: 730 | K3: Ambient | L3: Active | M3: =0.2*F3 -> 9 | N3: 500 | O3: =SUMIFS(Demand_Data!H3:H1082,Demand_Data!B3:B1082,Table2[[#This Row],[SKU_ID]],Demand_Data!F3:F1082,2024) -> 238145 | P3: =((2*Table2[[#This Row],[Annual demand]]*Table2[[#This Row],[Ordering cost]])/Table2[[#This Row],[Holding cost]])^(1/2) -> 5143.9825 | Q3: =STDEV(Demand_Data!B3:B1082,Table2[[#This Row],[SKU_ID]],Demand_Data!H3:H1082) -> 3434.5698 | R3: =1.65*Table2[[#This Row],[Std_Dev]]*(Table2[[#This Row],[Lead_Time_(Days)]]/30)^1/2 -> 1322.3094 | S3: =((Table2[[#This Row],[Annual demand]]/365)*Table2[[#This Row],[Lead_Time_(Days)]])+Table2[[#This Row],[Safety Stock]] -> 10456.638 | T3: =Table3[[#This Row],[Closing_Stock]]/(Table2[[#This Row],[Annual demand]]/365) -> 4.8417351
A4: SKU003 | B4: Vim Bar 200g | C4: Dishwash | D4: Bar | E4: Units | F4: 18 | G4: 28 | H4: 10 | I4: 2000 | J4: 365 | K4: Ambient | L4: Active | M4: =0.2*F4 -> 3.6 | N4: 500 | O4: =SUMIFS(Demand_Data!H4:H1083,Demand_Data!B4:B1083,Table2[[#This Row],[SKU_ID]],Demand_Data!F4:F1083,2024) -> 336966 | P4: =((2*Table2[[#This Row],[Annual demand]]*Table2[[#This Row],[Ordering cost]])/Table2[[#This Row],[Holding cost]])^(1/2) -> 9674.7954 | Q4: =STDEV(Demand_Data!B4:B1083,Table2[[#This Row],[SKU_ID]],Demand_Data!H4:H1083) -> 3435.9011 | R4: =1.65*Table2[[#This Row],[Std_Dev]]*(Table2[[#This Row],[Lead_Time_(Days)]]/30)^1/2 -> 944.8728 | S4: =((Table2[[#This Row],[Annual demand]]/365)*Table2[[#This Row],[Lead_Time_(Days)]])+Table2[[#This Row],[Safety Stock]] -> 10176.818 | T4: =Table3[[#This Row],[Closing_Stock]]/(Table2[[#This Row],[Annual demand]]/365) -> 3.3319089
A5: SKU004 | B5: Vim Liquid 500ml | C5: Dishwash | D5: Liquid | E5: Units | F5: 55 | G5: 90 | H5: 10 | I5: 500 | J5: 365 | K5: Ambient | L5: Active | M5: =0.2*F5 -> 11 | N5: 500 | O5: =SUMIFS(Demand_Data!H5:H1084,Demand_Data!B5:B1084,Table2[[#This Row],[SKU_ID]],Demand_Data!F5:F1084,2024) -> 111528 | P5: =((2*Table2[[#This Row],[Annual demand]]*Table2[[#This Row],[Ordering cost]])/Table2[[#This Row],[Holding cost]])^(1/2) -> 3184.1654 | Q5: =STDEV(Demand_Data!B5:B1084,Table2[[#This Row],[SKU_ID]],Demand_Data!H5:H1084) -> 3437.4686 | R5: =1.65*Table2[[#This Row],[Std_Dev]]*(Table2[[#This Row],[Lead_Time_(Days)]]/30)^1/2 -> 945.30385 | S5: =((Table2[[#This Row],[Annual demand]]/365)*Table2[[#This Row],[Lead_Time_(Days)]])+Table2[[#This Row],[Safety Stock]] -> 4000.8655 | T5: =Table3[[#This Row],[Closing_Stock]]/(Table2[[#This Row],[Annual demand]]/365) -> 23.360681
A6: SKU005 | B6: Lux Soap 100g | C6: Personal Care | D6: Bathing | E6: Units | F6: 22 | G6: 35 | H6: 7 | I6: 3000 | J6: 730 | K6: Ambient | L6: Active | M6: =0.2*F6 -> 4.4 | N6: 500 | O6: =SUMIFS(Demand_Data!H6:H1085,Demand_Data!B6:B1085,Table2[[#This Row],[SKU_ID]],Demand_Data!F6:F1085,2024) -> 422663 | P6: =((2*Table2[[#This Row],[Annual demand]]*Table2[[#This Row],[Ordering cost]])/Table2[[#This Row],[Holding cost]])^(1/2) -> 9801.0088 | Q6: =STDEV(Demand_Data!B6:B1085,Table2[[#This Row],[SKU_ID]],Demand_Data!H6:H1085) -> 3439.0527 | R6: =1.65*Table2[[#This Row],[Std_Dev]]*(Table2[[#This Row],[Lead_Time_(Days)]]/30)^1/2 -> 662.01765 | S6: =((Table2[[#This Row],[Annual demand]]/365)*Table2[[#This Row],[Lead_Time_(Days)]])+Table2[[#This Row],[Safety Stock]] -> 8767.8834 | T6: =Table3[[#This Row],[Closing_Stock]]/(Table2[[#This Row],[Annual demand]]/365) -> 3.0363197
A7: SKU006 | B7: Lifebuoy 125g | C7: Personal Care | D7: Bathing | E7: Units | F7: 25 | G7: 38 | H7: 7 | I7: 3000 | J7: 730 | K7: Ambient | L7: Active | M7: =0.2*F7 -> 5 | N7: 500 | O7: =SUMIFS(Demand_Data!H7:H1086,Demand_Data!B7:B1086,Table2[[#This Row],[SKU_ID]],Demand_Data!F7:F1086,2024) -> 389008 | P7: =((2*Table2[[#This Row],[Annual demand]]*Table2[[#This Row],[Ordering cost]])/Table2[[#This Row],[Holding cost]])^(1/2) -> 8820.5215 | Q7: =STDEV(Demand_Data!B7:B1086,Table2[[#This Row],[SKU_ID]],Demand_Data!H7:H1086) -> 3440.6182 | R7: =1.65*Table2[[#This Row],[Std_Dev]]*(Table2[[#This Row],[Lead_Time_(Days)]]/30)^1/2 -> 662.319 | S7: =((Table2[[#This Row],[Annual demand]]/365)*Table2[[#This Row],[Lead_Time_(Days)]])+Table2[[#This Row],[Safety Stock]] -> 8122.7464 | T7: =Table3[[#This Row],[Closing_Stock]]/(Table2[[#This Row],[Annual demand]]/365) -> 6.5051233
A8: SKU007 | B8: Dove Shampoo 180ml | C8: Personal Care | D8: Hair | E8: Units | F8: 120 | G8: 185 | H8: 21 | I8: 300 | J8: 730 | K8: Ambient | L8: Active | M8: =0.2*F8 -> 24 | N8: 500 | O8: =SUMIFS(Demand_Data!H8:H1087,Demand_Data!B8:B1087,Table2[[#This Row],[SKU_ID]],Demand_Data!F8:F1087,2024) -> 62512 | P8: =((2*Table2[[#This Row],[Annual demand]]*Table2[[#This Row],[Ordering cost]])/Table2[[#This Row],[Holding cost]])^(1/2) -> 1613.898 | Q8: =STDEV(Demand_Data!B8:B1087,Table2[[#This Row],[SKU_ID]],Demand_Data!H8:H1087) -> 3442.2222 | R8: =1.65*Table2[[#This Row],[Std_Dev]]*(Table2[[#This Row],[Lead_Time_(Days)]]/30)^1/2 -> 1987.8833 | S8: =((Table2[[#This Row],[Annual demand]]/365)*Table2[[#This Row],[Lead_Time_(Days)]])+Table2[[#This Row],[Safety Stock]] -> 5584.4641 | T8: =Table3[[#This Row],[Closing_Stock]]/(Table2[[#This Row],[Annual demand]]/365) -> 55.930621
A9: SKU008 | B9: Sunsilk Shampoo 180ml | C9: Personal Care | D9: Hair | E9: Units | F9: 90 | G9: 145 | H9: 21 | I9: 300 | J9: 730 | K9: Ambient | L9: Active | M9: =0.2*F9 -> 18 | N9: 500 | O9: =SUMIFS(Demand_Data!H9:H1088,Demand_Data!B9:B1088,Table2[[#This Row],[SKU_ID]],Demand_Data!F9:F1088,2024) -> 76299 | P9: =((2*Table2[[#This Row],[Annual demand]]*Table2[[#This Row],[Ordering cost]])/Table2[[#This Row],[Holding cost]])^(1/2) -> 2058.8427 | Q9: =STDEV(Demand_Data!B9:B1088,Table2[[#This Row],[SKU_ID]],Demand_Data!H9:H1088) -> 3443.8285 | R9: =1.65*Table2[[#This Row],[Std_Dev]]*(Table2[[#This Row],[Lead_Time_(Days)]]/30)^1/2 -> 1988.8109 | S9: =((Table2[[#This Row],[Annual demand]]/365)*Table2[[#This Row],[Lead_Time_(Days)]])+Table2[[#This Row],[Safety Stock]] -> 6378.6164 | T9: =Table3[[#This Row],[Closing_Stock]]/(Table2[[#This Row],[Annual demand]]/365) -> 43.035164
A10: SKU009 | B10: Vaseline 100ml | C10: Personal Care | D10: Skincare | E10: Units | F10: 65 | G10: 110 | H10: 14 | I10: 500 | J10: 1095 | K10: Ambient | L10: Active | M10: =0.2*F10 -> 13 | N10: 500 | O10: =SUMIFS(Demand_Data!H10:H1089,Demand_Data!B10:B1089,Table2[[#This Row],[SKU_ID]],Demand_Data!F10:F1089,2024) -> 96617 | P10: =((2*Table2[[#This Row],[Annual demand]]*Table2[[#This Row],[Ordering cost]])/Table2[[#This Row],[Holding cost]])^(1/2) -> 2726.1836 | Q10: =STDEV(Demand_Data!B10:B1089,Table2[[#This Row],[SKU_ID]],Demand_Data!H10:H1089) -> 3445.4089 | R10: =1.65*Table2[[#This Row],[Std_Dev]]*(Table2[[#This Row],[Lead_Time_(Days)]]/30)^1/2 -> 1326.4824 | S10: =((Table2[[#This Row],[Annual demand]]/365)*Table2[[#This Row],[Lead_Time_(Days)]])+Table2[[#This Row],[Safety Stock]] -> 5032.34 | T10: =Table3[[#This Row],[Closing_Stock]]/(Table2[[#This Row],[Annual demand]]/365) -> 26.573067
A11: SKU010 | B11: Clinic Plus 80ml | C11: Personal Care | D11: Hair | E11: Units | F11: 55 | G11: 85 | H11: 21 | I11: 500 | J11: 730 | K11: Ambient | L11: Active | M11: =0.2*F11 -> 11 | N11: 500 | O11: =SUMIFS(Demand_Data!H11:H1090,Demand_Data!B11:B1090,Table2[[#This Row],[SKU_ID]],Demand_Data!F11:F1090,2024) -> 124664 | P11: =((2*Table2[[#This Row],[Annual demand]]*Table2[[#This Row],[Ordering cost]])/Table2[[#This Row],[Holding cost]])^(1/2) -> 3366.4656 | Q11: =STDEV(Demand_Data!B11:B1090,Table2[[#This Row],[SKU_ID]],Demand_Data!H11:H1090) -> 3447.0126 | R11: =1.65*Table2[[#This Row],[Std_Dev]]*(Table2[[#This Row],[Lead_Time_(Days)]]/30)^1/2 -> 1990.6498 | S11: =((Table2[[#This Row],[Annual demand]]/365)*Table2[[#This Row],[Lead_Time_(Days)]])+Table2[[#This Row],[Safety Stock]] -> 9163.0991 | T11: =Table3[[#This Row],[Closing_Stock]]/(Table2[[#This Row],[Annual demand]]/365) -> 7.7032263
A12: SKU011 | B12: Rin Powder 1kg | C12: Detergent | D12: Laundry | E12: Units | F12: 70 | G12: 105 | H12: 14 | I12: 500 | J12: 730 | K12: Ambient | L12: Active | M12: =0.2*F12 -> 14 | N12: 500 | O12: =SUMIFS(Demand_Data!H12:H1091,Demand_Data!B12:B1091,Table2[[#This Row],[SKU_ID]],Demand_Data!F12:F1091,2024) -> 135191 | P12: =((2*Table2[[#This Row],[Annual demand]]*Table2[[#This Row],[Ordering cost]])/Table2[[#This Row],[Holding cost]])^(1/2) -> 3107.4909 | Q12: =STDEV(Demand_Data!B12:B1091,Table2[[#This Row],[SKU_ID]],Demand_Data!H12:H1091) -> 3448.6112 | R12: =1.65*Table2[[#This Row],[Std_Dev]]*(Table2[[#This Row],[Lead_Time_(Days)]]/30)^1/2 -> 1327.7153 | S12: =((Table2[[#This Row],[Annual demand]]/365)*Table2[[#This Row],[Lead_Time_(Days)]])+Table2[[#This Row],[Safety Stock]] -> 6513.1235 | T12: =Table3[[#This Row],[Closing_Stock]]/(Table2[[#This Row],[Annual demand]]/365) -> 6.3366274
A13: SKU012 | B13: Comfort 200ml | C13: Fabric Care | D13: Conditioner | E13: Units | F13: 45 | G13: 72 | H13: 14 | I13: 600 | J13: 365 | K13: Ambient | L13: Active | M13: =0.2*F13 -> 9 | N13: 500 | O13: =SUMIFS(Demand_Data!H13:H1092,Demand_Data!B13:B1092,Table2[[#This Row],[SKU_ID]],Demand_Data!F13:F1092,2024) -> 51712 | P13: =((2*Table2[[#This Row],[Annual demand]]*Table2[[#This Row],[Ordering cost]])/Table2[[#This Row],[Holding cost]])^(1/2) -> 2397.0352 | Q13: =STDEV(Demand_Data!B13:B1092,Table2[[#This Row],[SKU_ID]],Demand_Data!H13:H1092) -> 3450.2254 | R13: =1.65*Table2[[#This Row],[Std_Dev]]*(Table2[[#This Row],[Lead_Time_(Days)]]/30)^1/2 -> 1328.3368 | S13: =((Table2[[#This Row],[Annual demand]]/365)*Table2[[#This Row],[Lead_Time_(Days)]])+Table2[[#This Row],[Safety Stock]] -> 3311.8108 | T13: =Table3[[#This Row],[Closing_Stock]]/(Table2[[#This Row],[Annual demand]]/365) -> 13.749613
... A16: SKU015 | B16: Kissan Ketchup 500g | C16: Food | D16: Sauces | E16: Units | F16: 78 | G16: 125 | H16: 21 | I16: 200 | J16: 365 | K16: Cold | L16: Active | M16: =0.2*F16 -> 15.6 | N16: 500 | O16: =SUMIFS(Demand_Data!H16:H1095,Demand_Data!B16:B1095,Table2[[#This Row],[SKU_ID]],Demand_Data!F16:F1095,2024) -> 27550 | P16: =((2*Table2[[#This Row],[Annual demand]]*Table2[[#This Row],[Ordering cost]])/Table2[[#This Row],[Holding cost]])^(1/2) -> 1328.919 | Q16: =STDEV(Demand_Data!B16:B1095,Table2[[#This Row],[SKU_ID]],Demand_Data!H16:H1095) -> 3454.4737 | R16: =1.65*Table2[[#This Row],[Std_Dev]]*(Table2[[#This Row],[Lead_Time_(Days)]]/30)^1/2 -> 1994.9585 | S16: =((Table2[[#This Row],[Annual demand]]/365)*Table2[[#This Row],[Lead_Time_(Days)]])+Table2[[#This Row],[Safety Stock]] -> 3580.027 | T16: =Table3[[#This Row],[Closing_Stock]]/(Table2[[#This Row],[Annual demand]]/365) -> 220.55009

Sheet Demand-Pivot
B3: Column Labels
A4: Row Labels | B4: North | C4: South | D4: West | E4: Grand Total
A5: 01-01-2025
A6: Clinic Plus 80ml | B6: 4435.3333 | C6: 3681.6667 | D6: 4336.3333 | E6: 12453.333
A7: Close Up 80g | B7: 4873 | C7: 3960.6667 | D7: 4606.6667 | E7: 13440.333
A8: Comfort 200ml | B8: 1716.3333 | C8: 1428.3333 | D8: 1754.3333 | E8: 4899
A9: Dove Shampoo 180ml | B9: 2247 | C9: 1877.3333 | D9: 1890.6667 | E9: 6015
A10: Kissan Ketchup 500g | B10: 972.66667 | C10: 810 | D10: 865.33333 | E10: 2648
A11: Lifebuoy 125g | B11: 13765 | C11: 11862.667 | D11: 13030.667 | E11: 38658.333
A12: Lux Soap 100g | B12: 14589.667 | C12: 12122 | D12: 13605.333 | E12: 40317
A13: Pepsodent 150g | B13: 4646.3333 | C13: 4191 | D13: 4655 | E13: 13492.333
A14: Rin Powder 1kg | B14: 4733 | C14: 3858.3333 | D14: 4508 | E14: 13099.333
A15: Sunsilk Shampoo 180ml | B15: 2597 | C15: 2286.3333 | D15: 2475.6667 | E15: 7359
A16: Surf Excel 1kg | B16: 4946.6667 | C16: 4418 | D16: 4764.6667 | E16: 14129.333
A17: Surf Excel 500g | B17: 8273.3333 | C17: 7562 | D17: 8192.6667 | E17: 24028
... A20: Vim Liquid 500ml | B20: 3793 | C20: 3357 | D20: 3627.6667 | E20: 10777.667
A21: 01-02-2025
A22: Clinic Plus 80ml | B22: 4547.1111 | C22: 3719.5556 | D22: 4487.4444 | E22: 12754.111
A23: Close Up 80g | B23: 4954.6667 | C23: 4031.5556 | D23: 4698.2222 | E23: 13684.444
A24: Comfort 200ml | B24: 1792.1111 | C24: 1463.1111 | D24: 1758.1111 | E24: 5013.3333
A25: Dove Shampoo 180ml | B25: 2283.6667 | C25: 1942.1111 | D25: 1963.5556 | E25: 6189.3333
A26: Kissan Ketchup 500g | B26: 980.88889 | C26: 818.66667 | D26: 880.11111 | E26: 2679.6667
A27: Lifebuoy 125g | B27: 14162.667 | C27: 12446.222 | D27: 13397.889 | E27: 40006.778
A28: Lux Soap 100g | B28: 15173.222 | C28: 12062.667 | D28: 14321.111 | E28: 41557
A29: Pepsodent 150g | B29: 4784.4444 | C29: 4409.6667 | D29: 4765.3333 | E29: 13959.444
A30: Rin Powder 1kg | B30: 4805.6667 | C30: 4061.4444 | D30: 4687.3333 | E30: 13554.444
A31: Sunsilk Shampoo 180ml | B31: 2618.3333 | C31: 2412.1111 | D31: 2558.2222 | E31: 7588.6667
A32: Surf Excel 1kg | B32: 5214.2222 | C32: 4676.3333 | D32: 4836.2222 | E32: 14726.778
A33: Surf Excel 500g | B33: 8436.4444 | C33: 7760.6667 | D33: 8727.2222 | E33: 24924.333
... A36: Vim Liquid 500ml | B36: 3947 | C36: 3434 | D36: 3732.5556 | E36: 11113.556
A37: 01-03-2025
A38: Clinic Plus 80ml | B38: 4532.8148 | C38: 3689.4074 | D38: 4510.9259 | E38: 12733.148
A39: Close Up 80g | B39: 5125.5556 | C39: 4131.4074 | D39: 4881.6296 | E39: 14138.593
A40: Comfort 200ml | B40: 1768.1481 | C40: 1463.8148 | D40: 1768.1481 | E40: 5000.1111
A41: Dove Shampoo 180ml | B41: 2306.5556 | C41: 2012.8148 | D41: 1968.7407 | E41: 6288.1111
A42: Kissan Ketchup 500g | B42: 974.51852 | C42: 811.55556 | D42: 874.14815 | E42: 2660.2222
A43: Lifebuoy 125g | B43: 13782.222 | C43: 12369.296 | D43: 13370.852 | E43: 39522.37
A44: Lux Soap 100g | B44: 14654.296 | C44: 12268.222 | D44: 14089.481 | E44: 41012
A45: Pepsodent 150g | B45: 4795.5926 | C45: 4485.5556 | D45: 4807.1111 | E45: 14088.259
A46: Rin Powder 1kg | B46: 4838.5556 | C46: 4049.5926 | D46: 4804.4444 | E46: 13692.593
A47: Sunsilk Shampoo 180ml | B47: 2581.4444 | C47: 2471.4815 | D47: 2615.963 | E47: 7668.8889
A48: Surf Excel 1kg | B48: 5106.2963 | C48: 4733.7778 | D48: 4824.963 | E48: 14665.037
A49: Surf Excel 500g | B49: 8486.2593 | C49: 7842.8889 | D49: 8672.963 | E49: 25002.111
... A52: Vim Liquid 500ml | B52: 3898.6667 | C52: 3421 | D52: 3752.4074 | E52: 11072.074
A53: 01-04-2025
A54: Clinic Plus 80ml | B54: 4505.0864 | C54: 3696.8765 | D54: 4444.9012 | E54: 12646.864
A55: Close Up 80g | B55: 4984.4074 | C55: 4041.2099 | D55: 4728.8395 | E55: 13754.457
A56: Comfort 200ml | B56: 1758.8642 | C56: 1451.7531 | D56: 1760.1975 | E56: 4970.8148
A57: Dove Shampoo 180ml | B57: 2279.0741 | C57: 1944.0864 | D57: 1940.9877 | E57: 6164.1481
A58: Kissan Ketchup 500g | B58: 976.02469 | C58: 813.40741 | D58: 873.19753 | E58: 2662.6296
A59: Lifebuoy 125g | B59: 13903.296 | C59: 12226.062 | D59: 13266.469 | E59: 39395.827
A60: Lux Soap 100g | B60: 14805.728 | C60: 12150.963 | D60: 14005.309 | E60: 40962
A61: Pepsodent 150g | B61: 4742.1235 | C61: 4362.0741 | D61: 4742.4815 | E61: 13846.679
A62: Rin Powder 1kg | B62: 4792.4074 | C62: 3989.7901 | D62: 4666.5926 | E62: 13448.79
A63: Sunsilk Shampoo 180ml | B63: 2598.9259 | C63: 2389.9753 | D63: 2549.9506 | E63: 7538.8519
A64: Surf Excel 1kg | B64: 5089.0617 | C64: 4609.3704 | D64: 4808.6173 | E64: 14507.049
A65: Surf Excel 500g | B65: 8398.679 | C65: 7721.8519 | D65: 8530.9506 | E65: 24651.481
... A68: Vim Liquid 500ml | B68: 3879.5556 | C68: 3404 | D68: 3704.2099 | E68: 10987.765
A69: 01-05-2025
A70: Clinic Plus 80ml | B70: 4528.3374 | C70: 3701.9465 | D70: 4481.0905 | E70: 12711.374
A71: Close Up 80g | B71: 5021.5432 | C71: 4068.0576 | D71: 4769.5638 | E71: 13859.165
A72: Comfort 200ml | B72: 1773.0412 | C72: 1459.5597 | D72: 1762.1523 | E72: 4994.7531
A73: Dove Shampoo 180ml | B73: 2289.7654 | C73: 1966.3374 | D73: 1957.7613 | E73: 6213.8642
A74: Kissan Ketchup 500g | B74: 977.14403 | C74: 814.54321 | D74: 875.81893 | E74: 2667.5062
A75: Lifebuoy 125g | B75: 13949.395 | C75: 12347.193 | D75: 13345.07 | E75: 39641.658
A76: Lux Soap 100g | B76: 14877.749 | C76: 12160.617 | D76: 14138.634 | E76: 41177
A77: Pepsodent 150g | B77: 4774.0535 | C77: 4419.0988 | D77: 4771.642 | E77: 13964.794
A78: Rin Powder 1kg | B78: 4812.2099 | C78: 4033.6091 | D78: 4719.4568 | E78: 13565.276
A79: Sunsilk Shampoo 180ml | B79: 2599.5679 | C79: 2424.5226 | D79: 2574.7119 | E79: 7598.8025
A80: Surf Excel 1kg | B80: 5136.5267 | C80: 4673.1605 | D80: 4823.2675 | E80: 14632.955
A81: Surf Excel 500g | B81: 8440.4609 | C81: 7775.1358 | D81: 8643.7119 | E81: 24859.309
... A84: Vim Liquid 500ml | B84: 3908.4074 | C84: 3419.6667 | D84: 3729.7243 | E84: 11057.798
A85: 01-06-2025
A86: Clinic Plus 80ml | B86: 4522.0796 | C86: 3696.0768 | D86: 4478.9726 | E86: 12697.129
A87: Close Up 80g | B87: 5043.8354 | C87: 4080.225 | D87: 4793.3443 | E87: 13917.405
A88: Comfort 200ml | B88: 1766.6845 | C88: 1458.3759 | D88: 1763.4993 | E88: 4988.5597
A89: Dove Shampoo 180ml | B89: 2291.7984 | C89: 1974.4129 | D89: 1955.8299 | E89: 6222.0412
A90: Kissan Ketchup 500g | B90: 975.89575 | C90: 813.16872 | D90: 874.3882 | E90: 2663.4527
A91: Lifebuoy 125g | B91: 13878.305 | C91: 12314.184 | D91: 13327.464 | E91: 39519.952
A92: Lux Soap 100g | B92: 14779.258 | C92: 12193.267 | D92: 14077.808 | E92: 41050.333
A93: Pepsodent 150g | B93: 4770.5898 | C93: 4422.2428 | D93: 4773.7449 | E93: 13966.578
A94: Rin Powder 1kg | B94: 4814.3909 | C94: 4024.3306 | D94: 4730.1646 | E94: 13568.886
A95: Sunsilk Shampoo 180ml | B95: 2593.3128 | C95: 2428.6598 | D95: 2580.2085 | E95: 7602.1811
A96: Surf Excel 1kg | B96: 5110.6283 | C96: 4672.1029 | D96: 4818.9492 | E96: 14601.68
A97: Surf Excel 500g | B97: 8441.7997 | C97: 7779.9588 | D97: 8615.8752 | E97: 24837.634
... A106: Total 01-06-2025 | B106: 88791.741 | C106: 76132.291 | D106: 85247.069 | E106: 250171.1

Sheet Demand_Data
A1: Record_ID | B1: SKU_ID | C1: Product_Name | D1: Region | E1: Month | F1: Year | G1: Month_Year | H1: Actual_Demand_(Units) | I1: Forecast_(Units) | J1: Forecast_Error | K1: MAPE_(%) | L1: Channel | M1: Moving_Avg | N1: Exponential_Smoothing | O1: Error | P1: MAPE | Q1: MAPE(Exponential) | R1: model | S1: Avg_MAPE | T1: Product | U1: 01-01-2025 | V1: 01-02-2025 | W1: 01-03-2025 | X1: 01-04-2025 | Y1: 01-05-2025 | Z1: 01-06-2025 | AA1: region | AB1: Total forecast
A2: 1 | B2: SKU001 | C2: Surf Excel 1kg | D2: North | E2: 1 | F2: 2023 | G2: 44927 | H2: 3689 | I2: 3338 | J2: 351 | K2: 9.5 | L2: General Trade | N2: 3689 | O2: =ABS(H2-I2) -> 351 | P2: =ABS(O2)/H2 -> 0.095147737 | Q2: =ABS((H2-N2))/H2 -> 0 | R2: System Forecast | S2: =AVERAGE(P2:P1081) -> 0.051126695 | T2: Surf Excel 1kg | U2: =AVERAGEIFS($H$2:$H$1081,$C$2:$C$1081,$T2,$D$2:$D$1081,$AA2,$F$2:$F$1081,2024,$E$2:$E$1081,">=10") -> 4946.6667 | V2: =AVERAGE(AVERAGEIFS($H$2:$H$1081,$C$2:$C$1081,T2,$D$2:$D$1081,AA2,$F$2:$F$1081,2024,$E$2:$E$1081,"=11"),AVERAGEIFS($H$2:$H$1081,$C$2:$C$1081,T2,$D$2:$D$1081,AA2,$F$2:$F$1081,2024,$E$2:$E$1081,"=12"),U2) -> 5214.2222 | W2: =AVERAGE(AVERAGEIFS($H$2:$H$1081,$C$2:$C$1081,T2,$D$2:$D$1081,AA2,$F$2:$F$1081,2024,$E$2:$E$1081,"=12"),U2,V2) -> 5106.2963 | X2: =AVERAGE(U2,V2,W2) -> 5089.0617 | Y2: =AVERAGE(V2,W2,X2) -> 5136.5267 | Z2: =AVERAGE(W2,X2,Y2) -> 5110.6283 | AA2: North | AB2: =Table1[[#This Row],[01-01-2025]]+Table1[[#This Row],[01-02-2025]]+Table1[[#This Row],[01-03-2025]]+Table1[[#This Row],[01-04-2025]]+Table1[[#This Row],[01-05-2025]]+Table1[[#This Row],[01-06-2025]] -> 30603.402
A3: 2 | B3: SKU001 | C3: Surf Excel 1kg | D3: North | E3: 2 | F3: 2023 | G3: Feb-2023 | H3: 3233 | I3: 2999 | J3: 234 | K3: 7.2 | L3: Modern Trade | N3: =0.3*H2+(0.7*N2) -> 3689 | O3: =ABS(H3-I3) -> 234 | P3: =ABS(O3)/H3 -> 0.072378596 | Q3: =ABS((H3-N3))/H3 -> 0.14104547 | R3: Exponential Smoothing | S3: =AVERAGE(Q3:Q1081) -> 0.18296434 | T3: Surf Excel 1kg | U3: =AVERAGEIFS($H$2:$H$1081,$C$2:$C$1081,$T3,$D$2:$D$1081,$AA3,$F$2:$F$1081,2024,$E$2:$E$1081,">=10") -> 4418 | V3: =AVERAGE(AVERAGEIFS($H$2:$H$1081,$C$2:$C$1081,T3,$D$2:$D$1081,AA3,$F$2:$F$1081,2024,$E$2:$E$1081,"=11"),AVERAGEIFS($H$2:$H$1081,$C$2:$C$1081,T3,$D$2:$D$1081,AA3,$F$2:$F$1081,2024,$E$2:$E$1081,"=12"),U3) -> 4676.3333 | W3: =AVERAGE(AVERAGEIFS($H$2:$H$1081,$C$2:$C$1081,T3,$D$2:$D$1081,AA3,$F$2:$F$1081,2024,$E$2:$E$1081,"=12"),U3,V3) -> 4733.7778 | X3: =AVERAGE(U3,V3,W3) -> 4609.3704 | Y3: =AVERAGE(V3,W3,X3) -> 4673.1605 | Z3: =AVERAGE(W3,X3,Y3) -> 4672.1029 | AA3: South | AB3: =Table1[[#This Row],[01-01-2025]]+Table1[[#This Row],[01-02-2025]]+Table1[[#This Row],[01-03-2025]]+Table1[[#This Row],[01-04-2025]]+Table1[[#This Row],[01-05-2025]]+Table1[[#This Row],[01-06-2025]] -> 27782.745
A4: 3 | B4: SKU001 | C4: Surf Excel 1kg | D4: North | E4: 3 | F4: 2023 | G4: Mar-2023 | H4: 4159 | I4: 4485 | J4: -326 | K4: 7.8 | L4: Modern Trade | N4: =0.3*H3+(0.7*N3) -> 3552.2 | O4: =ABS(H4-I4) -> 326 | P4: =ABS(O4)/H4 -> 0.078384227 | Q4: =ABS((H4-N4))/H4 -> 0.14590046 | T4: Surf Excel 1kg | U4: =AVERAGEIFS($H$2:$H$1081,$C$2:$C$1081,$T4,$D$2:$D$1081,$AA4,$F$2:$F$1081,2024,$E$2:$E$1081,">=10") -> 4764.6667 | V4: =AVERAGE(AVERAGEIFS($H$2:$H$1081,$C$2:$C$1081,T4,$D$2:$D$1081,AA4,$F$2:$F$1081,2024,$E$2:$E$1081,"=11"),AVERAGEIFS($H$2:$H$1081,$C$2:$C$1081,T4,$D$2:$D$1081,AA4,$F$2:$F$1081,2024,$E$2:$E$1081,"=12"),U4) -> 4836.2222 | W4: =AVERAGE(AVERAGEIFS($H$2:$H$1081,$C$2:$C$1081,T4,$D$2:$D$1081,AA4,$F$2:$F$1081,2024,$E$2:$E$1081,"=12"),U4,V4) -> 4824.963 | X4: =AVERAGE(U4,V4,W4) -> 4808.6173 | Y4: =AVERAGE(V4,W4,X4) -> 4823.2675 | Z4: =AVERAGE(W4,X4,Y4) -> 4818.9492 | AA4: West | AB4: =Table1[[#This Row],[01-01-2025]]+Table1[[#This Row],[01-02-2025]]+Table1[[#This Row],[01-03-2025]]+Table1[[#This Row],[01-04-2025]]+Table1[[#This Row],[01-05-2025]]+Table1[[#This Row],[01-06-2025]] -> 28876.686
A5: 4 | B5: SKU001 | C5: Surf Excel 1kg | D5: North | E5: 4 | F5: 2023 | G5: Apr-2023 | H5: 4291 | I5: 3889 | J5: 402 | K5: 9.4 | L5: Modern Trade | M5: =AVERAGE(H2:H4) -> 3693.6667 | N5: =0.3*H4+(0.7*N4) -> 3734.24 | O5: =ABS(H5-I5) -> 402 | P5: =ABS(O5)/H5 -> 0.093684456 | Q5: =ABS((H5-N5))/H5 -> 0.12975064 | T5: =C75 -> Surf Excel 500g | U5: =AVERAGEIFS($H$2:$H$1081,$C$2:$C$1081,$T5,$D$2:$D$1081,$AA5,$F$2:$F$1081,2024,$E$2:$E$1081,">=10") -> 8273.3333 | V5: =AVERAGE(AVERAGEIFS($H$2:$H$1081,$C$2:$C$1081,T5,$D$2:$D$1081,AA5,$F$2:$F$1081,2024,$E$2:$E$1081,"=11"),AVERAGEIFS($H$2:$H$1081,$C$2:$C$1081,T5,$D$2:$D$1081,AA5,$F$2:$F$1081,2024,$E$2:$E$1081,"=12"),U5) -> 8436.4444 | W5: =AVERAGE(AVERAGEIFS($H$2:$H$1081,$C$2:$C$1081,T5,$D$2:$D$1081,AA5,$F$2:$F$1081,2024,$E$2:$E$1081,"=12"),U5,V5) -> 8486.2593 | X5: =AVERAGE(U5,V5,W5) -> 8398.679 | Y5: =AVERAGE(V5,W5,X5) -> 8440.4609 | Z5: =AVERAGE(W5,X5,Y5) -> 8441.7997 | AA5: North | AB5: =Table1[[#This Row],[01-01-2025]]+Table1[[#This Row],[01-02-2025]]+Table1[[#This Row],[01-03-2025]]+Table1[[#This Row],[01-04-2025]]+Table1[[#This Row],[01-05-2025]]+Table1[[#This Row],[01-06-2025]] -> 50476.977
A6: 5 | B6: SKU001 | C6: Surf Excel 1kg | D6: North | E6: 5 | F6: 2023 | G6: May-2023 | H6: 4112 | I6: 4116 | J6: -4 | K6: 0.1 | L6: Modern Trade | M6: =AVERAGE(H3:H5) -> 3894.3333 | N6: =0.3*H5+(0.7*N5) -> 3901.268 | O6: =ABS(H6-I6) -> 4 | P6: =ABS(O6)/H6 -> 0.00097276265 | Q6: =ABS((H6-N6))/H6 -> 0.051248054 | T6: =C75 -> Surf Excel 500g | U6: =AVERAGEIFS($H$2:$H$1081,$C$2:$C$1081,$T6,$D$2:$D$1081,$AA6,$F$2:$F$1081,2024,$E$2:$E$1081,">=10") -> 7562 | V6: =AVERAGE(AVERAGEIFS($H$2:$H$1081,$C$2:$C$1081,T6,$D$2:$D$1081,AA6,$F$2:$F$1081,2024,$E$2:$E$1081,"=11"),AVERAGEIFS($H$2:$H$1081,$C$2:$C$1081,T6,$D$2:$D$1081,AA6,$F$2:$F$1081,2024,$E$2:$E$1081,"=12"),U6) -> 7760.6667 | W6: =AVERAGE(AVERAGEIFS($H$2:$H$1081,$C$2:$C$1081,T6,$D$2:$D$1081,AA6,$F$2:$F$1081,2024,$E$2:$E$1081,"=12"),U6,V6) -> 7842.8889 | X6: =AVERAGE(U6,V6,W6) -> 7721.8519 | Y6: =AVERAGE(V6,W6,X6) -> 7775.1358 | Z6: =AVERAGE(W6,X6,Y6) -> 7779.9588 | AA6: South | AB6: =Table1[[#This Row],[01-01-2025]]+Table1[[#This Row],[01-02-2025]]+Table1[[#This Row],[01-03-2025]]+Table1[[#This Row],[01-04-2025]]+Table1[[#This Row],[01-05-2025]]+Table1[[#This Row],[01-06-2025]] -> 46442.502
A7: 6 | B7: SKU001 | C7: Surf Excel 1kg | D7: North | E7: 6 | F7: 2023 | G7: Jun-2023 | H7: 4687 | I7: 4889 | J7: -202 | K7: 4.3 | L7: E-Commerce | M7: =AVERAGE(H4:H6) -> 4187.3333 | N7: =0.3*H6+(0.7*N6) -> 3964.4876 | O7: =ABS(H7-I7) -> 202 | P7: =ABS(O7)/H7 -> 0.04309793 | Q7: =ABS((H7-N7))/H7 -> 0.15415242 | T7: =C75 -> Surf Excel 500g | U7: =AVERAGEIFS($H$2:$H$1081,$C$2:$C$1081,$T7,$D$2:$D$1081,$AA7,$F$2:$F$1081,2024,$E$2:$E$1081,">=10") -> 8192.6667 | V7: =AVERAGE(AVERAGEIFS($H$2:$H$1081,$C$2:$C$1081,T7,$D$2:$D$1081,AA7,$F$2:$F$1081,2024,$E$2:$E$1081,"=11"),AVERAGEIFS($H$2:$H$1081,$C$2:$C$1081,T7,$D$2:$D$1081,AA7,$F$2:$F$1081,2024,$E$2:$E$1081,"=12"),U7) -> 8727.2222 | W7: =AVERAGE(AVERAGEIFS($H$2:$H$1081,$C$2:$C$1081,T7,$D$2:$D$1081,AA7,$F$2:$F$1081,2024,$E$2:$E$1081,"=12"),U7,V7) -> 8672.963 | X7: =AVERAGE(U7,V7,W7) -> 8530.9506 | Y7: =AVERAGE(V7,W7,X7) -> 8643.7119 | Z7: =AVERAGE(W7,X7,Y7) -> 8615.8752 | AA7: West | AB7: =Table1[[#This Row],[01-01-2025]]+Table1[[#This Row],[01-02-2025]]+Table1[[#This Row],[01-03-2025]]+Table1[[#This Row],[01-04-2025]]+Table1[[#This Row],[01-05-2025]]+Table1[[#This Row],[01-06-2025]] -> 51383.39
A8: 7 | B8: SKU001 | C8: Surf Excel 1kg | D8: North | E8: 7 | F8: 2023 | G8: Jul-2023 | H8: 4584 | I8: 4327 | J8: 257 | K8: 5.6 | L8: E-Commerce | M8: =AVERAGE(H5:H7) -> 4363.3333 | N8: =0.3*H7+(0.7*N7) -> 4181.2413 | O8: =ABS(H8-I8) -> 257 | P8: =ABS(O8)/H8 -> 0.056064572 | Q8: =ABS((H8-N8))/H8 -> 0.087861841 | T8: =C146 -> Vim Bar 200g | U8: =AVERAGEIFS($H$2:$H$1081,$C$2:$C$1081,$T8,$D$2:$D$1081,$AA8,$F$2:$F$1081,2024,$E$2:$E$1081,">=10") -> 12287.667 | V8: =AVERAGE(AVERAGEIFS($H$2:$H$1081,$C$2:$C$1081,T8,$D$2:$D$1081,AA8,$F$2:$F$1081,2024,$E$2:$E$1081,"=11"),AVERAGEIFS($H$2:$H$1081,$C$2:$C$1081,T8,$D$2:$D$1081,AA8,$F$2:$F$1081,2024,$E$2:$E$1081,"=12"),U8) -> 12551.222 | W8: =AVERAGE(AVERAGEIFS($H$2:$H$1081,$C$2:$C$1081,T8,$D$2:$D$1081,AA8,$F$2:$F$1081,2024,$E$2:$E$1081,"=12"),U8,V8) -> 12490.296 | X8: =AVERAGE(U8,V8,W8) -> 12443.062 | Y8: =AVERAGE(V8,W8,X8) -> 12494.86 | Z8: =AVERAGE(W8,X8,Y8) -> 12476.073 | AA8: North | AB8: =Table1[[#This Row],[01-01-2025]]+Table1[[#This Row],[01-02-2025]]+Table1[[#This Row],[01-03-2025]]+Table1[[#This Row],[01-04-2025]]+Table1[[#This Row],[01-05-2025]]+Table1[[#This Row],[01-06-2025]] -> 74743.18
A9: 8 | B9: SKU001 | C9: Surf Excel 1kg | D9: North | E9: 8 | F9: 2023 | G9: Aug-2023 | H9: 4175 | I9: 4483 | J9: -308 | K9: 7.4 | L9: Modern Trade | M9: =AVERAGE(H6:H8) -> 4461 | N9: =0.3*H8+(0.7*N8) -> 4302.0689 | O9: =ABS(H9-I9) -> 308 | P9: =ABS(O9)/H9 -> 0.073772455 | Q9: =ABS((H9-N9))/H9 -> 0.03043567 | T9: =C146 -> Vim Bar 200g | U9: =AVERAGEIFS($H$2:$H$1081,$C$2:$C$1081,$T9,$D$2:$D$1081,$AA9,$F$2:$F$1081,2024,$E$2:$E$1081,">=10") -> 9737.3333 | V9: =AVERAGE(AVERAGEIFS($H$2:$H$1081,$C$2:$C$1081,T9,$D$2:$D$1081,AA9,$F$2:$F$1081,2024,$E$2:$E$1081,"=11"),AVERAGEIFS($H$2:$H$1081,$C$2:$C$1081,T9,$D$2:$D$1081,AA9,$F$2:$F$1081,2024,$E$2:$E$1081,"=12"),U9) -> 9957.1111 | W9: =AVERAGE(AVERAGEIFS($H$2:$H$1081,$C$2:$C$1081,T9,$D$2:$D$1081,AA9,$F$2:$F$1081,2024,$E$2:$E$1081,"=12"),U9,V9) -> 9796.4815 | X9: =AVERAGE(U9,V9,W9) -> 9830.3086 | Y9: =AVERAGE(V9,W9,X9) -> 9861.3004 | Z9: =AVERAGE(W9,X9,Y9) -> 9829.3635 | AA9: South | AB9: =Table1[[#This Row],[01-01-2025]]+Table1[[#This Row],[01-02-2025]]+Table1[[#This Row],[01-03-2025]]+Table1[[#This Row],[01-04-2025]]+Table1[[#This Row],[01-05-2025]]+Table1[[#This Row],[01-06-2025]] -> 59011.898
A10: 9 | B10: SKU001 | C10: Surf Excel 1kg | D10: North | E10: 9 | F10: 2023 | G10: Sep-2023 | H10: 4399 | I10: 4258 | J10: 141 | K10: 3.2 | L10: Modern Trade | M10: =AVERAGE(H7:H9) -> 4482 | N10: =0.3*H9+(0.7*N9) -> 4263.9482 | O10: =ABS(H10-I10) -> 141 | P10: =ABS(O10)/H10 -> 0.032052739 | Q10: =ABS((H10-N10))/H10 -> 0.030700558 | T10: =C146 -> Vim Bar 200g | U10: =AVERAGEIFS($H$2:$H$1081,$C$2:$C$1081,$T10,$D$2:$D$1081,$AA10,$F$2:$F$1081,2024,$E$2:$E$1081,">=10") -> 10959.333 | V10: =AVERAGE(AVERAGEIFS($H$2:$H$1081,$C$2:$C$1081,T10,$D$2:$D$1081,AA10,$F$2:$F$1081,2024,$E$2:$E$1081,"=11"),AVERAGEIFS($H$2:$H$1081,$C$2:$C$1081,T10,$D$2:$D$1081,AA10,$F$2:$F$1081,2024,$E$2:$E$1081,"=12"),U10) -> 11616.778 | W10: =AVERAGE(AVERAGEIFS($H$2:$H$1081,$C$2:$C$1081,T10,$D$2:$D$1081,AA10,$F$2:$F$1081,2024,$E$2:$E$1081,"=12"),U10,V10) -> 11375.37 | X10: =AVERAGE(U10,V10,W10) -> 11317.16 | Y10: =AVERAGE(V10,W10,X10) -> 11436.436 | Z10: =AVERAGE(W10,X10,Y10) -> 11376.322 | AA10: West | AB10: =Table1[[#This Row],[01-01-2025]]+Table1[[#This Row],[01-02-2025]]+Table1[[#This Row],[01-03-2025]]+Table1[[#This Row],[01-04-2025]]+Table1[[#This Row],[01-05-2025]]+Table1[[#This Row],[01-06-2025]] -> 68081.401
A11: 10 | B11: SKU001 | C11: Surf Excel 1kg | D11: North | E11: 10 | F11: 2023 | G11: Oct-2023 | H11: 4304 | I11: 4530 | J11: -226 | K11: 5.3 | L11: Modern Trade | M11: =AVERAGE(H8:H10) -> 4386 | N11: =0.3*H10+(0.7*N10) -> 4304.4638 | O11: =ABS(H11-I11) -> 226 | P11: =ABS(O11)/H11 -> 0.052509294 | Q11: =ABS((H11-N11))/H11 -> 0.00010775389 | T11: =C218 -> Vim Liquid 500ml | U11: =AVERAGEIFS($H$2:$H$1081,$C$2:$C$1081,$T11,$D$2:$D$1081,$AA11,$F$2:$F$1081,2024,$E$2:$E$1081,">=10") -> 3793 | V11: =AVERAGE(AVERAGEIFS($H$2:$H$1081,$C$2:$C$1081,T11,$D$2:$D$1081,AA11,$F$2:$F$1081,2024,$E$2:$E$1081,"=11"),AVERAGEIFS($H$2:$H$1081,$C$2:$C$1081,T11,$D$2:$D$1081,AA11,$F$2:$F$1081,2024,$E$2:$E$1081,"=12"),U11) -> 3947 | W11: =AVERAGE(AVERAGEIFS($H$2:$H$1081,$C$2:$C$1081,T11,$D$2:$D$1081,AA11,$F$2:$F$1081,2024,$E$2:$E$1081,"=12"),U11,V11) -> 3898.6667 | X11: =AVERAGE(U11,V11,W11) -> 3879.5556 | Y11: =AVERAGE(V11,W11,X11) -> 3908.4074 | Z11: =AVERAGE(W11,X11,Y11) -> 3895.5432 | AA11: North | AB11: =Table1[[#This Row],[01-01-2025]]+Table1[[#This Row],[01-02-2025]]+Table1[[#This Row],[01-03-2025]]+Table1[[#This Row],[01-04-2025]]+Table1[[#This Row],[01-05-2025]]+Table1[[#This Row],[01-06-2025]] -> 23322.173
A12: 11 | B12: SKU001 | C12: Surf Excel 1kg | D12: North | E12: 11 | F12: 2023 | G12: Nov-2023 | H12: 4736 | I12: 4354 | J12: 382 | K12: 8.1 | L12: General Trade | M12: =AVERAGE(H9:H11) -> 4292.6667 | N12: =0.3*H11+(0.7*N11) -> 4304.3246 | O12: =ABS(H12-I12) -> 382 | P12: =ABS(O12)/H12 -> 0.080658784 | Q12: =ABS((H12-N12))/H12 -> 0.091147669 | T12: =C218 -> Vim Liquid 500ml | U12: =AVERAGEIFS($H$2:$H$1081,$C$2:$C$1081,$T12,$D$2:$D$1081,$AA12,$F$2:$F$1081,2024,$E$2:$E$1081,">=10") -> 3357 | V12: =AVERAGE(AVERAGEIFS($H$2:$H$1081,$C$2:$C$1081,T12,$D$2:$D$1081,AA12,$F$2:$F$1081,2024,$E$2:$E$1081,"=11"),AVERAGEIFS($H$2:$H$1081,$C$2:$C$1081,T12,$D$2:$D$1081,AA12,$F$2:$F$1081,2024,$E$2:$E$1081,"=12"),U12) -> 3434 | W12: =AVERAGE(AVERAGEIFS($H$2:$H$1081,$C$2:$C$1081,T12,$D$2:$D$1081,AA12,$F$2:$F$1081,2024,$E$2:$E$1081,"=12"),U12,V12) -> 3421 | X12: =AVERAGE(U12,V12,W12) -> 3404 | Y12: =AVERAGE(V12,W12,X12) -> 3419.6667 | Z12: =AVERAGE(W12,X12,Y12) -> 3414.8889 | AA12: South | AB12: =Table1[[#This Row],[01-01-2025]]+Table1[[#This Row],[01-02-2025]]+Table1[[#This Row],[01-03-2025]]+Table1[[#This Row],[01-04-2025]]+Table1[[#This Row],[01-05-2025]]+Table1[[#This Row],[01-06-2025]] -> 20450.556
A13: 12 | B13: SKU001 | C13: Surf Excel 1kg | D13: North | E13: 12 | F13: 2023 | G13: Dec-2023 | H13: 5595 | I13: 5938 | J13: -343 | K13: 6.1 | L13: E-Commerce | M13: =AVERAGE(H10:H12) -> 4479.6667 | N13: =0.3*H12+(0.7*N12) -> 4433.8272 | O13: =ABS(H13-I13) -> 343 | P13: =ABS(O13)/H13 -> 0.061304736 | Q13: =ABS((H13-N13))/H13 -> 0.20753758 | T13: =C218 -> Vim Liquid 500ml | U13: =AVERAGEIFS($H$2:$H$1081,$C$2:$C$1081,$T13,$D$2:$D$1081,$AA13,$F$2:$F$1081,2024,$E$2:$E$1081,">=10") -> 3627.6667 | V13: =AVERAGE(AVERAGEIFS($H$2:$H$1081,$C$2:$C$1081,T13,$D$2:$D$1081,AA13,$F$2:$F$1081,2024,$E$2:$E$1081,"=11"),AVERAGEIFS($H$2:$H$1081,$C$2:$C$1081,T13,$D$2:$D$1081,AA13,$F$2:$F$1081,2024,$E$2:$E$1081,"=12"),U13) -> 3732.5556 | W13: =AVERAGE(AVERAGEIFS($H$2:$H$1081,$C$2:$C$1081,T13,$D$2:$D$1081,AA13,$F$2:$F$1081,2024,$E$2:$E$1081,"=12"),U13,V13) -> 3752.4074 | X13: =AVERAGE(U13,V13,W13) -> 3704.2099 | Y13: =AVERAGE(V13,W13,X13) -> 3729.7243 | Z13: =AVERAGE(W13,X13,Y13) -> 3728.7805 | AA13: West | AB13: =Table1[[#This Row],[01-01-2025]]+Table1[[#This Row],[01-02-2025]]+Table1[[#This Row],[01-03-2025]]+Table1[[#This Row],[01-04-2025]]+Table1[[#This Row],[01-05-2025]]+Table1[[#This Row],[01-06-2025]] -> 22275.344
A14: 13 | B14: SKU001 | C14: Surf Excel 1kg | D14: North | E14: 1 | F14: 2024 | G14: Jan-2024 | H14: 3535 | I14: 3269 | J14: 266 | K14: 7.5 | L14: General Trade | M14: =AVERAGE(H11:H13) -> 4878.3333 | N14: =0.3*H13+(0.7*N13) -> 4782.1791 | O14: =ABS(H14-I14) -> 266 | P14: =ABS(O14)/H14 -> 0.075247525 | Q14: =ABS((H14-N14))/H14 -> 0.35280879 | T14: =C290 -> Lux Soap 100g | U14: =AVERAGEIFS($H$2:$H$1081,$C$2:$C$1081,$T14,$D$2:$D$1081,$AA14,$F$2:$F$1081,2024,$E$2:$E$1081,">=10") -> 14589.667 | V14: =AVERAGE(AVERAGEIFS($H$2:$H$1081,$C$2:$C$1081,T14,$D$2:$D$1081,AA14,$F$2:$F$1081,2024,$E$2:$E$1081,"=11"),AVERAGEIFS($H$2:$H$1081,$C$2:$C$1081,T14,$D$2:$D$1081,AA14,$F$2:$F$1081,2024,$E$2:$E$1081,"=12"),U14) -> 15173.222 | W14: =AVERAGE(AVERAGEIFS($H$2:$H$1081,$C$2:$C$1081,T14,$D$2:$D$1081,AA14,$F$2:$F$1081,2024,$E$2:$E$1081,"=12"),U14,V14) -> 14654.296 | X14: =AVERAGE(U14,V14,W14) -> 14805.728 | Y14: =AVERAGE(V14,W14,X14) -> 14877.749 | Z14: =AVERAGE(W14,X14,Y14) -> 14779.258 | AA14: North | AB14: =Table1[[#This Row],[01-01-2025]]+Table1[[#This Row],[01-02-2025]]+Table1[[#This Row],[01-03-2025]]+Table1[[#This Row],[01-04-2025]]+Table1[[#This Row],[01-05-2025]]+Table1[[#This Row],[01-06-2025]] -> 88879.92
A15: 14 | B15: SKU001 | C15: Surf Excel 1kg | D15: North | E15: 2 | F15: 2024 | G15: Feb-2024 | H15: 3095 | I15: 2966 | J15: 129 | K15: 4.2 | L15: E-Commerce | M15: =AVERAGE(H12:H14) -> 4622 | N15: =0.3*H14+(0.7*N14) -> 4408.0254 | O15: =ABS(H15-I15) -> 129 | P15: =ABS(O15)/H15 -> 0.041680129 | Q15: =ABS((H15-N15))/H15 -> 0.42424082 | T15: =C290 -> Lux Soap 100g | U15: =AVERAGEIFS($H$2:$H$1081,$C$2:$C$1081,$T15,$D$2:$D$1081,$AA15,$F$2:$F$1081,2024,$E$2:$E$1081,">=10") -> 12122 | V15: =AVERAGE(AVERAGEIFS($H$2:$H$1081,$C$2:$C$1081,T15,$D$2:$D$1081,AA15,$F$2:$F$1081,2024,$E$2:$E$1081,"=11"),AVERAGEIFS($H$2:$H$1081,$C$2:$C$1081,T15,$D$2:$D$1081,AA15,$F$2:$F$1081,2024,$E$2:$E$1081,"=12"),U15) -> 12062.667 | W15: =AVERAGE(AVERAGEIFS($H$2:$H$1081,$C$2:$C$1081,T15,$D$2:$D$1081,AA15,$F$2:$F$1081,2024,$E$2:$E$1081,"=12"),U15,V15) -> 12268.222 | X15: =AVERAGE(U15,V15,W15) -> 12150.963 | Y15: =AVERAGE(V15,W15,X15) -> 12160.617 | Z15: =AVERAGE(W15,X15,Y15) -> 12193.267 | AA15: South | AB15: =Table1[[#This Row],[01-01-2025]]+Table1[[#This Row],[01-02-2025]]+Table1[[#This Row],[01-03-2025]]+Table1[[#This Row],[01-04-2025]]+Table1[[#This Row],[01-05-2025]]+Table1[[#This Row],[01-06-2025]] -> 72957.737
A16: 15 | B16: SKU001 | C16: Surf Excel 1kg | D16: North | E16: 3 | F16: 2024 | G16: Mar-2024 | H16: 4103 | I16: 4399 | J16: -296 | K16: 7.2 | L16: E-Commerce | M16: =AVERAGE(H13:H15) -> 4075 | N16: =0.3*H15+(0.7*N15) -> 4014.1177 | O16: =ABS(H16-I16) -> 296 | P16: =ABS(O16)/H16 -> 0.072142335 | Q16: =ABS((H16-N16))/H16 -> 0.021662748 | T16: =C290 -> Lux Soap 100g | U16: =AVERAGEIFS($H$2:$H$1081,$C$2:$C$1081,$T16,$D$2:$D$1081,$AA16,$F$2:$F$1081,2024,$E$2:$E$1081,">=10") -> 13605.333 | V16: =AVERAGE(AVERAGEIFS($H$2:$H$1081,$C$2:$C$1081,T16,$D$2:$D$1081,AA16,$F$2:$F$1081,2024,$E$2:$E$1081,"=11"),AVERAGEIFS($H$2:$H$1081,$C$2:$C$1081,T16,$D$2:$D$1081,AA16,$F$2:$F$1081,2024,$E$2:$E$1081,"=12"),U16) -> 14321.111 | W16: =AVERAGE(AVERAGEIFS($H$2:$H$1081,$C$2:$C$1081,T16,$D$2:$D$1081,AA16,$F$2:$F$1081,2024,$E$2:$E$1081,"=12"),U16,V16) -> 14089.481 | X16: =AVERAGE(U16,V16,W16) -> 14005.309 | Y16: =AVERAGE(V16,W16,X16) -> 14138.634 | Z16: =AVERAGE(W16,X16,Y16) -> 14077.808 | AA16: West | AB16: =Table1[[#This Row],[01-01-2025]]+Table1[[#This Row],[01-02-2025]]+Table1[[#This Row],[01-03-2025]]+Table1[[#This Row],[01-04-2025]]+Table1[[#This Row],[01-05-2025]]+Table1[[#This Row],[01-06-2025]] -> 84237.676
A17: 16 | B17: SKU001 | C17: Surf Excel 1kg | D17: North | E17: 4 | F17: 2024 | G17: Apr-2024 | H17: 3889 | I17: 3554 | J17: 335 | K17: 8.6 | L17: E-Commerce | M17: =AVERAGE(H14:H16) -> 3577.6667 | N17: =0.3*H16+(0.7*N16) -> 4040.7824 | O17: =ABS(H17-I17) -> 335 | P17: =ABS(O17)/H17 -> 0.086140396 | Q17: =ABS((H17-N17))/H17 -> 0.039028651 | T17: =C362 -> Lifebuoy 125g | U17: =AVERAGEIFS($H$2:$H$1081,$C$2:$C$1081,$T17,$D$2:$D$1081,$AA17,$F$2:$F$1081,2024,$E$2:$E$1081,">=10") -> 13765 | V17: =AVERAGE(AVERAGEIFS($H$2:$H$1081,$C$2:$C$1081,T17,$D$2:$D$1081,AA17,$F$2:$F$1081,2024,$E$2:$E$1081,"=11"),AVERAGEIFS($H$2:$H$1081,$C$2:$C$1081,T17,$D$2:$D$1081,AA17,$F$2:$F$1081,2024,$E$2:$E$1081,"=12"),U17) -> 14162.667 | W17: =AVERAGE(AVERAGEIFS($H$2:$H$1081,$C$2:$C$1081,T17,$D$2:$D$1081,AA17,$F$2:$F$1081,2024,$E$2:$E$1081,"=12"),U17,V17) -> 13782.222 | X17: =AVERAGE(U17,V17,W17) -> 13903.296 | Y17: =AVERAGE(V17,W17,X17) -> 13949.395 | Z17: =AVERAGE(W17,X17,Y17) -> 13878.305 | AA17: North | AB17: =Table1[[#This Row],[01-01-2025]]+Table1[[#This Row],[01-02-2025]]+Table1[[#This Row],[01-03-2025]]+Table1[[#This Row],[01-04-2025]]+Table1[[#This Row],[01-05-2025]]+Table1[[#This Row],[01-06-2025]] -> 83440.885
A18: 17 | B18: SKU001 | C18: Surf Excel 1kg | D18: North | E18: 5 | F18: 2024 | G18: May-2024 | H18: 4122 | I18: 3948 | J18: 174 | K18: 4.2 | L18: Modern Trade | M18: =AVERAGE(H15:H17) -> 3695.6667 | N18: =0.3*H17+(0.7*N17) -> 3995.2477 | O18: =ABS(H18-I18) -> 174 | P18: =ABS(O18)/H18 -> 0.042212518 | Q18: =ABS((H18-N18))/H18 -> 0.030750195 | T18: =C362 -> Lifebuoy 125g | U18: =AVERAGEIFS($H$2:$H$1081,$C$2:$C$1081,$T18,$D$2:$D$1081,$AA18,$F$2:$F$1081,2024,$E$2:$E$1081,">=10") -> 11862.667 | V18: =AVERAGE(AVERAGEIFS($H$2:$H$1081,$C$2:$C$1081,T18,$D$2:$D$1081,AA18,$F$2:$F$1081,2024,$E$2:$E$1081,"=11"),AVERAGEIFS($H$2:$H$1081,$C$2:$C$1081,T18,$D$2:$D$1081,AA18,$F$2:$F$1081,2024,$E$2:$E$1081,"=12"),U18) -> 12446.222 | W18: =AVERAGE(AVERAGEIFS($H$2:$H$1081,$C$2:$C$1081,T18,$D$2:$D$1081,AA18,$F$2:$F$1081,2024,$E$2:$E$1081,"=12"),U18,V18) -> 12369.296 | X18: =AVERAGE(U18,V18,W18) -> 12226.062 | Y18: =AVERAGE(V18,W18,X18) -> 12347.193 | Z18: =AVERAGE(W18,X18,Y18) -> 12314.184 | AA18: South | AB18: =Table1[[#This Row],[01-01-2025]]+Table1[[#This Row],[01-02-2025]]+Table1[[#This Row],[01-03-2025]]+Table1[[#This Row],[01-04-2025]]+Table1[[#This Row],[01-05-2025]]+Table1[[#This Row],[01-06-2025]] -> 73565.624
A19: 18 | B19: SKU001 | C19: Surf Excel 1kg | D19: North | E19: 6 | F19: 2024 | G19: Jun-2024 | H19: 5013 | I19: 5380 | J19: -367 | K19: 7.3 | L19: General Trade | M19: =AVERAGE(H16:H18) -> 4038 | N19: =0.3*H18+(0.7*N18) -> 4033.2734 | O19: =ABS(H19-I19) -> 367 | P19: =ABS(O19)/H19 -> 0.073209655 | Q19: =ABS((H19-N19))/H19 -> 0.19543719 | T19: =C362 -> Lifebuoy 125g | U19: =AVERAGEIFS($H$2:$H$1081,$C$2:$C$1081,$T19,$D$2:$D$1081,$AA19,$F$2:$F$1081,2024,$E$2:$E$1081,">=10") -> 13030.667 | V19: =AVERAGE(AVERAGEIFS($H$2:$H$1081,$C$2:$C$1081,T19,$D$2:$D$1081,AA19,$F$2:$F$1081,2024,$E$2:$E$1081,"=11"),AVERAGEIFS($H$2:$H$1081,$C$2:$C$1081,T19,$D$2:$D$1081,AA19,$F$2:$F$1081,2024,$E$2:$E$1081,"=12"),U19) -> 13397.889 | W19: =AVERAGE(AVERAGEIFS($H$2:$H$1081,$C$2:$C$1081,T19,$D$2:$D$1081,AA19,$F$2:$F$1081,2024,$E$2:$E$1081,"=12"),U19,V19) -> 13370.852 | X19: =AVERAGE(U19,V19,W19) -> 13266.469 | Y19: =AVERAGE(V19,W19,X19) -> 13345.07 | Z19: =AVERAGE(W19,X19,Y19) -> 13327.464 | AA19: West | AB19: =Table1[[#This Row],[01-01-2025]]+Table1[[#This Row],[01-02-2025]]+Table1[[#This Row],[01-03-2025]]+Table1[[#This Row],[01-04-2025]]+Table1[[#This Row],[01-05-2025]]+Table1[[#This Row],[01-06-2025]] -> 79738.41
A20: 19 | B20: SKU001 | C20: Surf Excel 1kg | D20: North | E20: 7 | F20: 2024 | G20: Jul-2024 | H20: 4294 | I20: 4410 | J20: -116 | K20: 2.7 | L20: General Trade | M20: =AVERAGE(H17:H19) -> 4341.3333 | N20: =0.3*H19+(0.7*N19) -> 4327.1914 | O20: =ABS(H20-I20) -> 116 | P20: =ABS(O20)/H20 -> 0.027014439 | Q20: =ABS((H20-N20))/H20 -> 0.0077297091 | T20: =C435 -> Dove Shampoo 180ml | U20: =AVERAGEIFS($H$2:$H$1081,$C$2:$C$1081,$T20,$D$2:$D$1081,$AA20,$F$2:$F$1081,2024,$E$2:$E$1081,">=10") -> 2247 | V20: =AVERAGE(AVERAGEIFS($H$2:$H$1081,$C$2:$C$1081,T20,$D$2:$D$1081,AA20,$F$2:$F$1081,2024,$E$2:$E$1081,"=11"),AVERAGEIFS($H$2:$H$1081,$C$2:$C$1081,T20,$D$2:$D$1081,AA20,$F$2:$F$1081,2024,$E$2:$E$1081,"=12"),U20) -> 2283.6667 | W20: =AVERAGE(AVERAGEIFS($H$2:$H$1081,$C$2:$C$1081,T20,$D$2:$D$1081,AA20,$F$2:$F$1081,2024,$E$2:$E$1081,"=12"),U20,V20) -> 2306.5556 | X20: =AVERAGE(U20,V20,W20) -> 2279.0741 | Y20: =AVERAGE(V20,W20,X20) -> 2289.7654 | Z20: =AVERAGE(W20,X20,Y20) -> 2291.7984 | AA20: North | AB20: =Table1[[#This Row],[01-01-2025]]+Table1[[#This Row],[01-02-2025]]+Table1[[#This Row],[01-03-2025]]+Table1[[#This Row],[01-04-2025]]+Table1[[#This Row],[01-05-2025]]+Table1[[#This Row],[01-06-2025]] -> 13697.86
A21: 20 | B21: SKU001 | C21: Surf Excel 1kg | D21: North | E21: 8 | F21: 2024 | G21: Aug-2024 | H21: 4052 | I21: 3934 | J21: 118 | K21: 2.9 | L21: E-Commerce | M21: =AVERAGE(H18:H20) -> 4476.3333 | N21: =0.3*H20+(0.7*N20) -> 4317.234 | O21: =ABS(H21-I21) -> 118 | P21: =ABS(O21)/H21 -> 0.029121422 | Q21: =ABS((H21-N21))/H21 -> 0.065457542 | T21: =C435 -> Dove Shampoo 180ml | U21: =AVERAGEIFS($H$2:$H$1081,$C$2:$C$1081,$T21,$D$2:$D$1081,$AA21,$F$2:$F$1081,2024,$E$2:$E$1081,">=10") -> 1877.3333 | V21: =AVERAGE(AVERAGEIFS($H$2:$H$1081,$C$2:$C$1081,T21,$D$2:$D$1081,AA21,$F$2:$F$1081,2024,$E$2:$E$1081,"=11"),AVERAGEIFS($H$2:$H$1081,$C$2:$C$1081,T21,$D$2:$D$1081,AA21,$F$2:$F$1081,2024,$E$2:$E$1081,"=12"),U21) -> 1942.1111 | W21: =AVERAGE(AVERAGEIFS($H$2:$H$1081,$C$2:$C$1081,T21,$D$2:$D$1081,AA21,$F$2:$F$1081,2024,$E$2:$E$1081,"=12"),U21,V21) -> 2012.8148 | X21: =AVERAGE(U21,V21,W21) -> 1944.0864 | Y21: =AVERAGE(V21,W21,X21) -> 1966.3374 | Z21: =AVERAGE(W21,X21,Y21) -> 1974.4129 | AA21: South | AB21: =Table1[[#This Row],[01-01-2025]]+Table1[[#This Row],[01-02-2025]]+Table1[[#This Row],[01-03-2025]]+Table1[[#This Row],[01-04-2025]]+Table1[[#This Row],[01-05-2025]]+Table1[[#This Row],[01-06-2025]] -> 11717.096
A22: 21 | B22: SKU001 | C22: Surf Excel 1kg | D22: North | E22: 9 | F22: 2024 | G22: Sep-2024 | H22: 3965 | I22: 4311 | J22: -346 | K22: 8.7 | L22: E-Commerce | M22: =AVERAGE(H19:H21) -> 4453 | N22: =0.3*H21+(0.7*N21) -> 4237.6638 | O22: =ABS(H22-I22) -> 346 | P22: =ABS(O22)/H22 -> 0.087263556 | Q22: =ABS((H22-N22))/H22 -> 0.06876766 | T22: =C435 -> Dove Shampoo 180ml | U22: =AVERAGEIFS($H$2:$H$1081,$C$2:$C$1081,$T22,$D$2:$D$1081,$AA22,$F$2:$F$1081,2024,$E$2:$E$1081,">=10") -> 1890.6667 | V22: =AVERAGE(AVERAGEIFS($H$2:$H$1081,$C$2:$C$1081,T22,$D$2:$D$1081,AA22,$F$2:$F$1081,2024,$E$2:$E$1081,"=11"),AVERAGEIFS($H$2:$H$1081,$C$2:$C$1081,T22,$D$2:$D$1081,AA22,$F$2:$F$1081,2024,$E$2:$E$1081,"=12"),U22) -> 1963.5556 | W22: =AVERAGE(AVERAGEIFS($H$2:$H$1081,$C$2:$C$1081,T22,$D$2:$D$1081,AA22,$F$2:$F$1081,2024,$E$2:$E$1081,"=12"),U22,V22) -> 1968.7407 | X22: =AVERAGE(U22,V22,W22) -> 1940.9877 | Y22: =AVERAGE(V22,W22,X22) -> 1957.7613 | Z22: =AVERAGE(W22,X22,Y22) -> 1955.8299 | AA22: West | AB22: =Table1[[#This Row],[01-01-2025]]+Table1[[#This Row],[01-02-2025]]+Table1[[#This Row],[01-03-2025]]+Table1[[#This Row],[01-04-2025]]+Table1[[#This Row],[01-05-2025]]+Table1[[#This Row],[01-06-2025]] -> 11677.542
A23: 22 | B23: SKU001 | C23: Surf Excel 1kg | D23: North | E23: 10 | F23: 2024 | G23: Oct-2024 | H23: 4144 | I23: 4255 | J23: -111 | K23: 2.7 | L23: E-Commerce | M23: =AVERAGE(H20:H22) -> 4103.6667 | N23: =0.3*H22+(0.7*N22) -> 4155.8646 | O23: =ABS(H23-I23) -> 111 | P23: =ABS(O23)/H23 -> 0.026785714 | Q23: =ABS((H23-N23))/H23 -> 0.0028630889 | T23: =C506 -> Sunsilk Shampoo 180ml | U23: =AVERAGEIFS($H$2:$H$1081,$C$2:$C$1081,$T23,$D$2:$D$1081,$AA23,$F$2:$F$1081,2024,$E$2:$E$1081,">=10") -> 2597 | V23: =AVERAGE(AVERAGEIFS($H$2:$H$1081,$C$2:$C$1081,T23,$D$2:$D$1081,AA23,$F$2:$F$1081,2024,$E$2:$E$1081,"=11"),AVERAGEIFS($H$2:$H$1081,$C$2:$C$1081,T23,$D$2:$D$1081,AA23,$F$2:$F$1081,2024,$E$2:$E$1081,"=12"),U23) -> 2618.3333 | W23: =AVERAGE(AVERAGEIFS($H$2:$H$1081,$C$2:$C$1081,T23,$D$2:$D$1081,AA23,$F$2:$F$1081,2024,$E$2:$E$1081,"=12"),U23,V23) -> 2581.4444 | X23: =AVERAGE(U23,V23,W23) -> 2598.9259 | Y23: =AVERAGE(V23,W23,X23) -> 2599.5679 | Z23: =AVERAGE(W23,X23,Y23) -> 2593.3128 | AA23: North | AB23: =Table1[[#This Row],[01-01-2025]]+Table1[[#This Row],[01-02-2025]]+Table1[[#This Row],[01-03-2025]]+Table1[[#This Row],[01-04-2025]]+Table1[[#This Row],[01-05-2025]]+Table1[[#This Row],[01-06-2025]] -> 15588.584
A24: 23 | B24: SKU001 | C24: Surf Excel 1kg | D24: North | E24: 11 | F24: 2024 | G24: Nov-2024 | H24: 5538 | I24: 5165 | J24: 373 | K24: 6.7 | L24: General Trade | M24: =AVERAGE(H21:H23) -> 4053.6667 | N24: =0.3*H23+(0.7*N23) -> 4152.3052 | O24: =ABS(H24-I24) -> 373 | P24: =ABS(O24)/H24 -> 0.067352835 | Q24: =ABS((H24-N24))/H24 -> 0.25021574 | T24: =C506 -> Sunsilk Shampoo 180ml | U24: =AVERAGEIFS($H$2:$H$1081,$C$2:$C$1081,$T24,$D$2:$D$1081,$AA24,$F$2:$F$1081,2024,$E$2:$E$1081,">=10") -> 2286.3333 | V24: =AVERAGE(AVERAGEIFS($H$2:$H$1081,$C$2:$C$1081,T24,$D$2:$D$1081,AA24,$F$2:$F$1081,2024,$E$2:$E$1081,"=11"),AVERAGEIFS($H$2:$H$1081,$C$2:$C$1081,T24,$D$2:$D$1081,AA24,$F$2:$F$1081,2024,$E$2:$E$1081,"=12"),U24) -> 2412.1111 | W24: =AVERAGE(AVERAGEIFS($H$2:$H$1081,$C$2:$C$1081,T24,$D$2:$D$1081,AA24,$F$2:$F$1081,2024,$E$2:$E$1081,"=12"),U24,V24) -> 2471.4815 | X24: =AVERAGE(U24,V24,W24) -> 2389.9753 | Y24: =AVERAGE(V24,W24,X24) -> 2424.5226 | Z24: =AVERAGE(W24,X24,Y24) -> 2428.6598 | AA24: South | AB24: =Table1[[#This Row],[01-01-2025]]+Table1[[#This Row],[01-02-2025]]+Table1[[#This Row],[01-03-2025]]+Table1[[#This Row],[01-04-2025]]+Table1[[#This Row],[01-05-2025]]+Table1[[#This Row],[01-06-2025]] -> 14413.084
A25: 24 | B25: SKU001 | C25: Surf Excel 1kg | D25: North | E25: 12 | F25: 2024 | G25: Dec-2024 | H25: 5158 | I25: 5596 | J25: -438 | K25: 8.5 | L25: E-Commerce | M25: =AVERAGE(H22:H24) -> 4549 | N25: =0.3*H24+(0.7*N24) -> 4568.0137 | O25: =ABS(H25-I25) -> 438 | P25: =ABS(O25)/H25 -> 0.084916634 | Q25: =ABS((H25-N25))/H25 -> 0.11438277 | T25: =C506 -> Sunsilk Shampoo 180ml | U25: =AVERAGEIFS($H$2:$H$1081,$C$2:$C$1081,$T25,$D$2:$D$1081,$AA25,$F$2:$F$1081,2024,$E$2:$E$1081,">=10") -> 2475.6667 | V25: =AVERAGE(AVERAGEIFS($H$2:$H$1081,$C$2:$C$1081,T25,$D$2:$D$1081,AA25,$F$2:$F$1081,2024,$E$2:$E$1081,"=11"),AVERAGEIFS($H$2:$H$1081,$C$2:$C$1081,T25,$D$2:$D$1081,AA25,$F$2:$F$1081,2024,$E$2:$E$1081,"=12"),U25) -> 2558.2222 | W25: =AVERAGE(AVERAGEIFS($H$2:$H$1081,$C$2:$C$1081,T25,$D$2:$D$1081,AA25,$F$2:$F$1081,2024,$E$2:$E$1081,"=12"),U25,V25) -> 2615.963 | X25: =AVERAGE(U25,V25,W25) -> 2549.9506 | Y25: =AVERAGE(V25,W25,X25) -> 2574.7119 | Z25: =AVERAGE(W25,X25,Y25) -> 2580.2085 | AA25: West | AB25: =Table1[[#This Row],[01-01-2025]]+Table1[[#This Row],[01-02-2025]]+Table1[[#This Row],[01-03-2025]]+Table1[[#This Row],[01-04-2025]]+Table1[[#This Row],[01-05-2025]]+Table1[[#This Row],[01-06-2025]] -> 15354.723
A26: 25 | B26: SKU001 | C26: Surf Excel 1kg | D26: South | E26: 1 | F26: 2023 | G26: Jan-2023 | H26: 3075 | I26: 3188 | J26: -113 | K26: 3.7 | L26: Modern Trade | M26: =AVERAGE(H23:H25) -> 4946.6667 | N26: =0.3*H25+(0.7*N25) -> 4745.0096 | O26: =ABS(H26-I26) -> 113 | P26: =ABS(O26)/H26 -> 0.036747967 | Q26: =ABS((H26-N26))/H26 -> 0.54309254 | T26: =C649 -> Vaseline 100ml | U26: =AVERAGEIFS($H$2:$H$1081,$C$2:$C$1081,$T26,$D$2:$D$1081,$AA26,$F$2:$F$1081,2024,$E$2:$E$1081,">=10") -> 3385 | V26: =AVERAGE(AVERAGEIFS($H$2:$H$1081,$C$2:$C$1081,T26,$D$2:$D$1081,AA26,$F$2:$F$1081,2024,$E$2:$E$1081,"=11"),AVERAGEIFS($H$2:$H$1081,$C$2:$C$1081,T26,$D$2:$D$1081,AA26,$F$2:$F$1081,2024,$E$2:$E$1081,"=12"),U26) -> 3503.3333 | W26: =AVERAGE(AVERAGEIFS($H$2:$H$1081,$C$2:$C$1081,T26,$D$2:$D$1081,AA26,$F$2:$F$1081,2024,$E$2:$E$1081,"=12"),U26,V26) -> 3411.7778 | X26: =AVERAGE(U26,V26,W26) -> 3433.3704 | Y26: =AVERAGE(V26,W26,X26) -> 3449.4938 | Z26: =AVERAGE(W26,X26,Y26) -> 3431.5473 | AA26: North | AB26: =Table1[[#This Row],[01-01-2025]]+Table1[[#This Row],[01-02-2025]]+Table1[[#This Row],[01-03-2025]]+Table1[[#This Row],[01-04-2025]]+Table1[[#This Row],[01-05-2025]]+Table1[[#This Row],[01-06-2025]] -> 20614.523
A27: 26 | B27: SKU001 | C27: Surf Excel 1kg | D27: South | E27: 2 | F27: 2023 | G27: Feb-2023 | H27: 2737 | I27: 2480 | J27: 257 | K27: 9.4 | L27: General Trade | M27: =AVERAGE(H24:H26) -> 4590.3333 | N27: =0.3*H26+(0.7*N26) -> 4244.0067 | O27: =ABS(H27-I27) -> 257 | P27: =ABS(O27)/H27 -> 0.093898429 | Q27: =ABS((H27-N27))/H27 -> 0.5506053 | T27: =C649 -> Vaseline 100ml | U27: =AVERAGEIFS($H$2:$H$1081,$C$2:$C$1081,$T27,$D$2:$D$1081,$AA27,$F$2:$F$1081,2024,$E$2:$E$1081,">=10") -> 2859 | V27: =AVERAGE(AVERAGEIFS($H$2:$H$1081,$C$2:$C$1081,T27,$D$2:$D$1081,AA27,$F$2:$F$1081,2024,$E$2:$E$1081,"=11"),AVERAGEIFS($H$2:$H$1081,$C$2:$C$1081,T27,$D$2:$D$1081,AA27,$F$2:$F$1081,2024,$E$2:$E$1081,"=12"),U27) -> 3033.6667 | W27: =AVERAGE(AVERAGEIFS($H$2:$H$1081,$C$2:$C$1081,T27,$D$2:$D$1081,AA27,$F$2:$F$1081,2024,$E$2:$E$1081,"=12"),U27,V27) -> 3072.8889 | X27: =AVERAGE(U27,V27,W27) -> 2988.5185 | Y27: =AVERAGE(V27,W27,X27) -> 3031.6914 | Z27: =AVERAGE(W27,X27,Y27) -> 3031.0329 | AA27: South | AB27: =Table1[[#This Row],[01-01-2025]]+Table1[[#This Row],[01-02-2025]]+Table1[[#This Row],[01-03-2025]]+Table1[[#This Row],[01-04-2025]]+Table1[[#This Row],[01-05-2025]]+Table1[[#This Row],[01-06-2025]] -> 18016.798
A28: 27 | B28: SKU001 | C28: Surf Excel 1kg | D28: South | E28: 3 | F28: 2023 | G28: Mar-2023 | H28: 3311 | I28: 3023 | J28: 288 | K28: 8.7 | L28: E-Commerce | M28: =AVERAGE(H25:H27) -> 3656.6667 | N28: =0.3*H27+(0.7*N27) -> 3791.9047 | O28: =ABS(H28-I28) -> 288 | P28: =ABS(O28)/H28 -> 0.086982785 | Q28: =ABS((H28-N28))/H28 -> 0.14524455 | T28: =C649 -> Vaseline 100ml | U28: =AVERAGEIFS($H$2:$H$1081,$C$2:$C$1081,$T28,$D$2:$D$1081,$AA28,$F$2:$F$1081,2024,$E$2:$E$1081,">=10") -> 3244.3333 | V28: =AVERAGE(AVERAGEIFS($H$2:$H$1081,$C$2:$C$1081,T28,$D$2:$D$1081,AA28,$F$2:$F$1081,2024,$E$2:$E$1081,"=11"),AVERAGEIFS($H$2:$H$1081,$C$2:$C$1081,T28,$D$2:$D$1081,AA28,$F$2:$F$1081,2024,$E$2:$E$1081,"=12"),U28) -> 3375.7778 | W28: =AVERAGE(AVERAGEIFS($H$2:$H$1081,$C$2:$C$1081,T28,$D$2:$D$1081,AA28,$F$2:$F$1081,2024,$E$2:$E$1081,"=12"),U28,V28) -> 3368.037 | X28: =AVERAGE(U28,V28,W28) -> 3329.3827 | Y28: =AVERAGE(V28,W28,X28) -> 3357.7325 | Z28: =AVERAGE(W28,X28,Y28) -> 3351.7174 | AA28: West | AB28: =Table1[[#This Row],[01-01-2025]]+Table1[[#This Row],[01-02-2025]]+Table1[[#This Row],[01-03-2025]]+Table1[[#This Row],[01-04-2025]]+Table1[[#This Row],[01-05-2025]]+Table1[[#This Row],[01-06-2025]] -> 20026.981
A29: 28 | B29: SKU001 | C29: Surf Excel 1kg | D29: South | E29: 4 | F29: 2023 | G29: Apr-2023 | H29: 3892 | I29: 3747 | J29: 145 | K29: 3.7 | L29: E-Commerce | M29: =AVERAGE(H26:H28) -> 3041 | N29: =0.3*H28+(0.7*N28) -> 3647.6333 | O29: =ABS(H29-I29) -> 145 | P29: =ABS(O29)/H29 -> 0.03725591 | Q29: =ABS((H29-N29))/H29 -> 0.062786926 | T29: =C650 -> Clinic Plus 80ml | U29: =AVERAGEIFS($H$2:$H$1081,$C$2:$C$1081,$T29,$D$2:$D$1081,$AA29,$F$2:$F$1081,2024,$E$2:$E$1081,">=10") -> 4435.3333 | V29: =AVERAGE(AVERAGEIFS($H$2:$H$1081,$C$2:$C$1081,T29,$D$2:$D$1081,AA29,$F$2:$F$1081,2024,$E$2:$E$1081,"=11"),AVERAGEIFS($H$2:$H$1081,$C$2:$C$1081,T29,$D$2:$D$1081,AA29,$F$2:$F$1081,2024,$E$2:$E$1081,"=12"),U29) -> 4547.1111 | W29: =AVERAGE(AVERAGEIFS($H$2:$H$1081,$C$2:$C$1081,T29,$D$2:$D$1081,AA29,$F$2:$F$1081,2024,$E$2:$E$1081,"=12"),U29,V29) -> 4532.8148 | X29: =AVERAGE(U29,V29,W29) -> 4505.0864 | Y29: =AVERAGE(V29,W29,X29) -> 4528.3374 | Z29: =AVERAGE(W29,X29,Y29) -> 4522.0796 | AA29: North | AB29: =Table1[[#This Row],[01-01-2025]]+Table1[[#This Row],[01-02-2025]]+Table1[[#This Row],[01-03-2025]]+Table1[[#This Row],[01-04-2025]]+Table1[[#This Row],[01-05-2025]]+Table1[[#This Row],[01-06-2025]] -> 27070.763
A30: 29 | B30: SKU001 | C30: Surf Excel 1kg | D30: South | E30: 5 | F30: 2023 | G30: May-2023 | H30: 3747 | I30: 4035 | J30: -288 | K30: 7.7 | L30: E-Commerce | M30: =AVERAGE(H27:H29) -> 3313.3333 | N30: =0.3*H29+(0.7*N29) -> 3720.9433 | O30: =ABS(H30-I30) -> 288 | P30: =ABS(O30)/H30 -> 0.076861489 | Q30: =ABS((H30-N30))/H30 -> 0.006954017 | T30: =C650 -> Clinic Plus 80ml | U30: =AVERAGEIFS($H$2:$H$1081,$C$2:$C$1081,$T30,$D$2:$D$1081,$AA30,$F$2:$F$1081,2024,$E$2:$E$1081,">=10") -> 3681.6667 | V30: =AVERAGE(AVERAGEIFS($H$2:$H$1081,$C$2:$C$1081,T30,$D$2:$D$1081,AA30,$F$2:$F$1081,2024,$E$2:$E$1081,"=11"),AVERAGEIFS($H$2:$H$1081,$C$2:$C$1081,T30,$D$2:$D$1081,AA30,$F$2:$F$1081,2024,$E$2:$E$1081,"=12"),U30) -> 3719.5556 | W30: =AVERAGE(AVERAGEIFS($H$2:$H$1081,$C$2:$C$1081,T30,$D$2:$D$1081,AA30,$F$2:$F$1081,2024,$E$2:$E$1081,"=12"),U30,V30) -> 3689.4074 | X30: =AVERAGE(U30,V30,W30) -> 3696.8765 | Y30: =AVERAGE(V30,W30,X30) -> 3701.9465 | Z30: =AVERAGE(W30,X30,Y30) -> 3696.0768 | AA30: South | AB30: =Table1[[#This Row],[01-01-2025]]+Table1[[#This Row],[01-02-2025]]+Table1[[#This Row],[01-03-2025]]+Table1[[#This Row],[01-04-2025]]+Table1[[#This Row],[01-05-2025]]+Table1[[#This Row],[01-06-2025]] -> 22185.529
A31: 30 | B31: SKU001 | C31: Surf Excel 1kg | D31: South | E31: 6 | F31: 2023 | G31: Jun-2023 | H31: 3888 | I31: 3705 | J31: 183 | K31: 4.7 | L31: Modern Trade | M31: =AVERAGE(H28:H30) -> 3650 | N31: =0.3*H30+(0.7*N30) -> 3728.7603 | O31: =ABS(H31-I31) -> 183 | P31: =ABS(O31)/H31 -> 0.047067901 | Q31: =ABS((H31-N31))/H31 -> 0.040956711 | T31: =C650 -> Clinic Plus 80ml | U31: =AVERAGEIFS($H$2:$H$1081,$C$2:$C$1081,$T31,$D$2:$D$1081,$AA31,$F$2:$F$1081,2024,$E$2:$E$1081,">=10") -> 4336.3333 | V31: =AVERAGE(AVERAGEIFS($H$2:$H$1081,$C$2:$C$1081,T31,$D$2:$D$1081,AA31,$F$2:$F$1081,2024,$E$2:$E$1081,"=11"),AVERAGEIFS($H$2:$H$1081,$C$2:$C$1081,T31,$D$2:$D$1081,AA31,$F$2:$F$1081,2024,$E$2:$E$1081,"=12"),U31) -> 4487.4444 | W31: =AVERAGE(AVERAGEIFS($H$2:$H$1081,$C$2:$C$1081,T31,$D$2:$D$1081,AA31,$F$2:$F$1081,2024,$E$2:$E$1081,"=12"),U31,V31) -> 4510.9259 | X31: =AVERAGE(U31,V31,W31) -> 4444.9012 | Y31: =AVERAGE(V31,W31,X31) -> 4481.0905 | Z31: =AVERAGE(W31,X31,Y31) -> 4478.9726 | AA31: West | AB31: =Table1[[#This Row],[01-01-2025]]+Table1[[#This Row],[01-02-2025]]+Table1[[#This Row],[01-03-2025]]+Table1[[#This Row],[01-04-2025]]+Table1[[#This Row],[01-05-2025]]+Table1[[#This Row],[01-06-2025]] -> 26739.668
A32: 31 | B32: SKU001 | C32: Surf Excel 1kg | D32: South | E32: 7 | F32: 2023 | G32: Jul-2023 | H32: 4082 | I32: 4113 | J32: -31 | K32: 0.8 | L32: E-Commerce | M32: =AVERAGE(H29:H31) -> 3842.3333 | N32: =0.3*H31+(0.7*N31) -> 3776.5322 | O32: =ABS(H32-I32) -> 31 | P32: =ABS(O32)/H32 -> 0.0075943165 | Q32: =ABS((H32-N32))/H32 -> 0.074832872 | T32: =C722 -> Rin Powder 1kg | U32: =AVERAGEIFS($H$2:$H$1081,$C$2:$C$1081,$T32,$D$2:$D$1081,$AA32,$F$2:$F$1081,2024,$E$2:$E$1081,">=10") -> 4733 | V32: =AVERAGE(AVERAGEIFS($H$2:$H$1081,$C$2:$C$1081,T32,$D$2:$D$1081,AA32,$F$2:$F$1081,2024,$E$2:$E$1081,"=11"),AVERAGEIFS($H$2:$H$1081,$C$2:$C$1081,T32,$D$2:$D$1081,AA32,$F$2:$F$1081,2024,$E$2:$E$1081,"=12"),U32) -> 4805.6667 | W32: =AVERAGE(AVERAGEIFS($H$2:$H$1081,$C$2:$C$1081,T32,$D$2:$D$1081,AA32,$F$2:$F$1081,2024,$E$2:$E$1081,"=12"),U32,V32) -> 4838.5556 | X32: =AVERAGE(U32,V32,W32) -> 4792.4074 | Y32: =AVERAGE(V32,W32,X32) -> 4812.2099 | Z32: =AVERAGE(W32,X32,Y32) -> 4814.3909 | AA32: North | AB32: =Table1[[#This Row],[01-01-2025]]+Table1[[#This Row],[01-02-2025]]+Table1[[#This Row],[01-03-2025]]+Table1[[#This Row],[01-04-2025]]+Table1[[#This Row],[01-05-2025]]+Table1[[#This Row],[01-06-2025]] -> 28796.23
A33: 32 | B33: SKU001 | C33: Surf Excel 1kg | D33: South | E33: 8 | F33: 2023 | G33: Aug-2023 | H33: 3824 | I33: 4128 | J33: -304 | K33: 7.9 | L33: General Trade | M33: =AVERAGE(H30:H32) -> 3905.6667 | N33: =0.3*H32+(0.7*N32) -> 3868.1726 | O33: =ABS(H33-I33) -> 304 | P33: =ABS(O33)/H33 -> 0.079497908 | Q33: =ABS((H33-N33))/H33 -> 0.011551399 | T33: =C722 -> Rin Powder 1kg | U33: =AVERAGEIFS($H$2:$H$1081,$C$2:$C$1081,$T33,$D$2:$D$1081,$AA33,$F$2:$F$1081,2024,$E$2:$E$1081,">=10") -> 3858.3333 | V33: =AVERAGE(AVERAGEIFS($H$2:$H$1081,$C$2:$C$1081,T33,$D$2:$D$1081,AA33,$F$2:$F$1081,2024,$E$2:$E$1081,"=11"),AVERAGEIFS($H$2:$H$1081,$C$2:$C$1081,T33,$D$2:$D$1081,AA33,$F$2:$F$1081,2024,$E$2:$E$1081,"=12"),U33) -> 4061.4444 | W33: =AVERAGE(AVERAGEIFS($H$2:$H$1081,$C$2:$C$1081,T33,$D$2:$D$1081,AA33,$F$2:$F$1081,2024,$E$2:$E$1081,"=12"),U33,V33) -> 4049.5926 | X33: =AVERAGE(U33,V33,W33) -> 3989.7901 | Y33: =AVERAGE(V33,W33,X33) -> 4033.6091 | Z33: =AVERAGE(W33,X33,Y33) -> 4024.3306 | AA33: South | AB33: =Table1[[#This Row],[01-01-2025]]+Table1[[#This Row],[01-02-2025]]+Table1[[#This Row],[01-03-2025]]+Table1[[#This Row],[01-04-2025]]+Table1[[#This Row],[01-05-2025]]+Table1[[#This Row],[01-06-2025]] -> 24017.1
A34: 33 | B34: SKU001 | C34: Surf Excel 1kg | D34: South | E34: 9 | F34: 2023 | G34: Sep-2023 | H34: 3451 | I34: 3794 | J34: -343 | K34: 9.9 | L34: Modern Trade | M34: =AVERAGE(H31:H33) -> 3931.3333 | N34: =0.3*H33+(0.7*N33) -> 3854.9208 | O34: =ABS(H34-I34) -> 343 | P34: =ABS(O34)/H34 -> 0.099391481 | Q34: =ABS((H34-N34))/H34 -> 0.11704456 | T34: =C722 -> Rin Powder 1kg | U34: =AVERAGEIFS($H$2:$H$1081,$C$2:$C$1081,$T34,$D$2:$D$1081,$AA34,$F$2:$F$1081,2024,$E$2:$E$1081,">=10") -> 4508 | V34: =AVERAGE(AVERAGEIFS($H$2:$H$1081,$C$2:$C$1081,T34,$D$2:$D$1081,AA34,$F$2:$F$1081,2024,$E$2:$E$1081,"=11"),AVERAGEIFS($H$2:$H$1081,$C$2:$C$1081,T34,$D$2:$D$1081,AA34,$F$2:$F$1081,2024,$E$2:$E$1081,"=12"),U34) -> 4687.3333 | W34: =AVERAGE(AVERAGEIFS($H$2:$H$1081,$C$2:$C$1081,T34,$D$2:$D$1081,AA34,$F$2:$F$1081,2024,$E$2:$E$1081,"=12"),U34,V34) -> 4804.4444 | X34: =AVERAGE(U34,V34,W34) -> 4666.5926 | Y34: =AVERAGE(V34,W34,X34) -> 4719.4568 | Z34: =AVERAGE(W34,X34,Y34) -> 4730.1646 | AA34: West | AB34: =Table1[[#This Row],[01-01-2025]]+Table1[[#This Row],[01-02-2025]]+Table1[[#This Row],[01-03-2025]]+Table1[[#This Row],[01-04-2025]]+Table1[[#This Row],[01-05-2025]]+Table1[[#This Row],[01-06-2025]] -> 28115.992
A35: 34 | B35: SKU001 | C35: Surf Excel 1kg | D35: South | E35: 10 | F35: 2023 | G35: Oct-2023 | H35: 3935 | I35: 3613 | J35: 322 | K35: 8.2 | L35: Modern Trade | M35: =AVERAGE(H32:H34) -> 3785.6667 | N35: =0.3*H34+(0.7*N34) -> 3733.7446 | O35: =ABS(H35-I35) -> 322 | P35: =ABS(O35)/H35 -> 0.081829733 | Q35: =ABS((H35-N35))/H35 -> 0.051144968 | T35: =C794 -> Comfort 200ml | U35: =AVERAGEIFS($H$2:$H$1081,$C$2:$C$1081,$T35,$D$2:$D$1081,$AA35,$F$2:$F$1081,2024,$E$2:$E$1081,">=10") -> 1716.3333 | V35: =AVERAGE(AVERAGEIFS($H$2:$H$1081,$C$2:$C$1081,T35,$D$2:$D$1081,AA35,$F$2:$F$1081,2024,$E$2:$E$1081,"=11"),AVERAGEIFS($H$2:$H$1081,$C$2:$C$1081,T35,$D$2:$D$1081,AA35,$F$2:$F$1081,2024,$E$2:$E$1081,"=12"),U35) -> 1792.1111 | W35: =AVERAGE(AVERAGEIFS($H$2:$H$1081,$C$2:$C$1081,T35,$D$2:$D$1081,AA35,$F$2:$F$1081,2024,$E$2:$E$1081,"=12"),U35,V35) -> 1768.1481 | X35: =AVERAGE(U35,V35,W35) -> 1758.8642 | Y35: =AVERAGE(V35,W35,X35) -> 1773.0412 | Z35: =AVERAGE(W35,X35,Y35) -> 1766.6845 | AA35: North | AB35: =Table1[[#This Row],[01-01-2025]]+Table1[[#This Row],[01-02-2025]]+Table1[[#This Row],[01-03-2025]]+Table1[[#This Row],[01-04-2025]]+Table1[[#This Row],[01-05-2025]]+Table1[[#This Row],[01-06-2025]] -> 10575.182
A36: 35 | B36: SKU001 | C36: Surf Excel 1kg | D36: South | E36: 11 | F36: 2023 | G36: Nov-2023 | H36: 4849 | I36: 4512 | J36: 337 | K36: 6.9 | L36: Modern Trade | M36: =AVERAGE(H33:H35) -> 3736.6667 | N36: =0.3*H35+(0.7*N35) -> 3794.1212 | O36: =ABS(H36-I36) -> 337 | P36: =ABS(O36)/H36 -> 0.069498866 | Q36: =ABS((H36-N36))/H36 -> 0.21754564 | T36: =C794 -> Comfort 200ml | U36: =AVERAGEIFS($H$2:$H$1081,$C$2:$C$1081,$T36,$D$2:$D$1081,$AA36,$F$2:$F$1081,2024,$E$2:$E$1081,">=10") -> 1428.3333 | V36: =AVERAGE(AVERAGEIFS($H$2:$H$1081,$C$2:$C$1081,T36,$D$2:$D$1081,AA36,$F$2:$F$1081,2024,$E$2:$E$1081,"=11"),AVERAGEIFS($H$2:$H$1081,$C$2:$C$1081,T36,$D$2:$D$1081,AA36,$F$2:$F$1081,2024,$E$2:$E$1081,"=12"),U36) -> 1463.1111 | W36: =AVERAGE(AVERAGEIFS($H$2:$H$1081,$C$2:$C$1081,T36,$D$2:$D$1081,AA36,$F$2:$F$1081,2024,$E$2:$E$1081,"=12"),U36,V36) -> 1463.8148 | X36: =AVERAGE(U36,V36,W36) -> 1451.7531 | Y36: =AVERAGE(V36,W36,X36) -> 1459.5597 | Z36: =AVERAGE(W36,X36,Y36) -> 1458.3759 | AA36: South | AB36: =Table1[[#This Row],[01-01-2025]]+Table1[[#This Row],[01-02-2025]]+Table1[[#This Row],[01-03-2025]]+Table1[[#This Row],[01-04-2025]]+Table1[[#This Row],[01-05-2025]]+Table1[[#This Row],[01-06-2025]] -> 8724.9479
T37: =C794 -> Comfort 200ml | U37: =AVERAGEIFS($H$2:$H$1081,$C$2:$C$1081,$T37,$D$2:$D$1081,$AA37,$F$2:$F$1081,2024,$E$2:$E$1081,">=10") -> 1754.3333 | V37: =AVERAGE(AVERAGEIFS($H$2:$H$1081,$C$2:$C$1081,T37,$D$2:$D$1081,AA37,$F$2:$F$1081,2024,$E$2:$E$1081,"=11"),AVERAGEIFS($H$2:$H$1081,$C$2:$C$1081,T37,$D$2:$D$1081,AA37,$F$2:$F$1081,2024,$E$2:$E$1081,"=12"),U37) -> 1758.1111 | W37: =AVERAGE(AVERAGEIFS($H$2:$H$1081,$C$2:$C$1081,T37,$D$2:$D$1081,AA37,$F$2:$F$1081,2024,$E$2:$E$1081,"=12"),U37,V37) -> 1768.1481 | X37: =AVERAGE(U37,V37,W37) -> 1760.1975 | Y37: =AVERAGE(V37,W37,X37) -> 1762.1523 | Z37: =AVERAGE(W37,X37,Y37) -> 1763.4993 | AA37: West | AB37: =Table1[[#This Row],[01-01-2025]]+Table1[[#This Row],[01-02-2025]]+Table1[[#This Row],[01-03-2025]]+Table1[[#This Row],[01-04-2025]]+Table1[[#This Row],[01-05-2025]]+Table1[[#This Row],[01-06-2025]] -> 10566.442
A38: 37 | B38: SKU001 | C38: Surf Excel 1kg | D38: South | E38: 1 | F38: 2024 | G38: Jan-2024 | H38: 2950 | I38: 3006 | J38: -56 | K38: 1.9 | L38: General Trade | M38: =AVERAGE(H35:H37) -> 4392 | N38: =0.3*H37+(0.7*N37) -> 0 | O38: =ABS(H38-I38) -> 56 | P38: =ABS(O38)/H38 -> 0.018983051 | Q38: =ABS((H38-N38))/H38 -> 1 | T38: =C913 -> Pepsodent 150g | U38: =AVERAGEIFS($H$2:$H$1081,$C$2:$C$1081,$T38,$D$2:$D$1081,$AA38,$F$2:$F$1081,2024,$E$2:$E$1081,">=10") -> 4646.3333 | V38: =AVERAGE(AVERAGEIFS($H$2:$H$1081,$C$2:$C$1081,T38,$D$2:$D$1081,AA38,$F$2:$F$1081,2024,$E$2:$E$1081,"=11"),AVERAGEIFS($H$2:$H$1081,$C$2:$C$1081,T38,$D$2:$D$1081,AA38,$F$2:$F$1081,2024,$E$2:$E$1081,"=12"),U38) -> 4784.4444 | W38: =AVERAGE(AVERAGEIFS($H$2:$H$1081,$C$2:$C$1081,T38,$D$2:$D$1081,AA38,$F$2:$F$1081,2024,$E$2:$E$1081,"=12"),U38,V38) -> 4795.5926 | X38: =AVERAGE(U38,V38,W38) -> 4742.1235 | Y38: =AVERAGE(V38,W38,X38) -> 4774.0535 | Z38: =AVERAGE(W38,X38,Y38) -> 4770.5898 | AA38: North | AB38: =Table1[[#This Row],[01-01-2025]]+Table1[[#This Row],[01-02-2025]]+Table1[[#This Row],[01-03-2025]]+Table1[[#This Row],[01-04-2025]]+Table1[[#This Row],[01-05-2025]]+Table1[[#This Row],[01-06-2025]] -> 28513.137
A39: 38 | B39: SKU001 | C39: Surf Excel 1kg | D39: South | E39: 2 | F39: 2024 | G39: Feb-2024 | H39: 2947 | I39: 3224 | J39: -277 | K39: 9.4 | L39: Modern Trade | M39: =AVERAGE(H36:H38) -> 3899.5 | N39: =0.3*H38+(0.7*N38) -> 885 | O39: =ABS(H39-I39) -> 277 | P39: =ABS(O39)/H39 -> 0.093993892 | Q39: =ABS((H39-N39))/H39 -> 0.6996946 | T39: =C913 -> Pepsodent 150g | U39: =AVERAGEIFS($H$2:$H$1081,$C$2:$C$1081,$T39,$D$2:$D$1081,$AA39,$F$2:$F$1081,2024,$E$2:$E$1081,">=10") -> 4191 | V39: =AVERAGE(AVERAGEIFS($H$2:$H$1081,$C$2:$C$1081,T39,$D$2:$D$1081,AA39,$F$2:$F$1081,2024,$E$2:$E$1081,"=11"),AVERAGEIFS($H$2:$H$1081,$C$2:$C$1081,T39,$D$2:$D$1081,AA39,$F$2:$F$1081,2024,$E$2:$E$1081,"=12"),U39) -> 4409.6667 | W39: =AVERAGE(AVERAGEIFS($H$2:$H$1081,$C$2:$C$1081,T39,$D$2:$D$1081,AA39,$F$2:$F$1081,2024,$E$2:$E$1081,"=12"),U39,V39) -> 4485.5556 | X39: =AVERAGE(U39,V39,W39) -> 4362.0741 | Y39: =AVERAGE(V39,W39,X39) -> 4419.0988 | Z39: =AVERAGE(W39,X39,Y39) -> 4422.2428 | AA39: South | AB39: =Table1[[#This Row],[01-01-2025]]+Table1[[#This Row],[01-02-2025]]+Table1[[#This Row],[01-03-2025]]+Table1[[#This Row],[01-04-2025]]+Table1[[#This Row],[01-05-2025]]+Table1[[#This Row],[01-06-2025]] -> 26289.638
A40: 39 | B40: SKU001 | C40: Surf Excel 1kg | D40: South | E40: 3 | F40: 2024 | G40: Mar-2024 | H40: 3538 | I40: 3265 | J40: 273 | K40: 7.7 | L40: E-Commerce | M40: =AVERAGE(H37:H39) -> 2948.5 | N40: =0.3*H39+(0.7*N39) -> 1503.6 | O40: =ABS(H40-I40) -> 273 | P40: =ABS(O40)/H40 -> 0.077162239 | Q40: =ABS((H40-N40))/H40 -> 0.57501413 | T40: =C913 -> Pepsodent 150g | U40: =AVERAGEIFS($H$2:$H$1081,$C$2:$C$1081,$T40,$D$2:$D$1081,$AA40,$F$2:$F$1081,2024,$E$2:$E$1081,">=10") -> 4655 | V40: =AVERAGE(AVERAGEIFS($H$2:$H$1081,$C$2:$C$1081,T40,$D$2:$D$1081,AA40,$F$2:$F$1081,2024,$E$2:$E$1081,"=11"),AVERAGEIFS($H$2:$H$1081,$C$2:$C$1081,T40,$D$2:$D$1081,AA40,$F$2:$F$1081,2024,$E$2:$E$1081,"=12"),U40) -> 4765.3333 | W40: =AVERAGE(AVERAGEIFS($H$2:$H$1081,$C$2:$C$1081,T40,$D$2:$D$1081,AA40,$F$2:$F$1081,2024,$E$2:$E$1081,"=12"),U40,V40) -> 4807.1111 | X40: =AVERAGE(U40,V40,W40) -> 4742.4815 | Y40: =AVERAGE(V40,W40,X40) -> 4771.642 | Z40: =AVERAGE(W40,X40,Y40) -> 4773.7449 | AA40: West | AB40: =Table1[[#This Row],[01-01-2025]]+Table1[[#This Row],[01-02-2025]]+Table1[[#This Row],[01-03-2025]]+Table1[[#This Row],[01-04-2025]]+Table1[[#This Row],[01-05-2025]]+Table1[[#This Row],[01-06-2025]] -> 28515.313
A41: 40 | B41: SKU001 | C41: Surf Excel 1kg | D41: South | E41: 4 | F41: 2024 | G41: Apr-2024 | H41: 3784 | I41: 3987 | J41: -203 | K41: 5.4 | L41: General Trade | M41: =AVERAGE(H38:H40) -> 3145 | N41: =0.3*H40+(0.7*N40) -> 2113.92 | O41: =ABS(H41-I41) -> 203 | P41: =ABS(O41)/H41 -> 0.053646934 | Q41: =ABS((H41-N41))/H41 -> 0.44135307 | T41: =C938 -> Close Up 80g | U41: =AVERAGEIFS($H$2:$H$1081,$C$2:$C$1081,$T41,$D$2:$D$1081,$AA41,$F$2:$F$1081,2024,$E$2:$E$1081,">=10") -> 4873 | V41: =AVERAGE(AVERAGEIFS($H$2:$H$1081,$C$2:$C$1081,T41,$D$2:$D$1081,AA41,$F$2:$F$1081,2024,$E$2:$E$1081,"=11"),AVERAGEIFS($H$2:$H$1081,$C$2:$C$1081,T41,$D$2:$D$1081,AA41,$F$2:$F$1081,2024,$E$2:$E$1081,"=12"),U41) -> 4954.6667 | W41: =AVERAGE(AVERAGEIFS($H$2:$H$1081,$C$2:$C$1081,T41,$D$2:$D$1081,AA41,$F$2:$F$1081,2024,$E$2:$E$1081,"=12"),U41,V41) -> 5125.5556 | X41: =AVERAGE(U41,V41,W41) -> 4984.4074 | Y41: =AVERAGE(V41,W41,X41) -> 5021.5432 | Z41: =AVERAGE(W41,X41,Y41) -> 5043.8354 | AA41: North | AB41: =Table1[[#This Row],[01-01-2025]]+Table1[[#This Row],[01-02-2025]]+Table1[[#This Row],[01-03-2025]]+Table1[[#This Row],[01-04-2025]]+Table1[[#This Row],[01-05-2025]]+Table1[[#This Row],[01-06-2025]] -> 30003.008
A42: 41 | B42: SKU001 | C42: Surf Excel 1kg | D42: South | E42: 5 | F42: 2024 | G42: May-2024 | H42: 3399 | I42: 3354 | J42: 45 | K42: 1.3 | L42: General Trade | M42: =AVERAGE(H39:H41) -> 3423 | N42: =0.3*H41+(0.7*N41) -> 2614.944 | O42: =ABS(H42-I42) -> 45 | P42: =ABS(O42)/H42 -> 0.013239188 | Q42: =ABS((H42-N42))/H42 -> 0.23067255 | T42: =C938 -> Close Up 80g | U42: =AVERAGEIFS($H$2:$H$1081,$C$2:$C$1081,$T42,$D$2:$D$1081,$AA42,$F$2:$F$1081,2024,$E$2:$E$1081,">=10") -> 3960.6667 | V42: =AVERAGE(AVERAGEIFS($H$2:$H$1081,$C$2:$C$1081,T42,$D$2:$D$1081,AA42,$F$2:$F$1081,2024,$E$2:$E$1081,"=11"),AVERAGEIFS($H$2:$H$1081,$C$2:$C$1081,T42,$D$2:$D$1081,AA42,$F$2:$F$1081,2024,$E$2:$E$1081,"=12"),U42) -> 4031.5556 | W42: =AVERAGE(AVERAGEIFS($H$2:$H$1081,$C$2:$C$1081,T42,$D$2:$D$1081,AA42,$F$2:$F$1081,2024,$E$2:$E$1081,"=12"),U42,V42) -> 4131.4074 | X42: =AVERAGE(U42,V42,W42) -> 4041.2099 | Y42: =AVERAGE(V42,W42,X42) -> 4068.0576 | Z42: =AVERAGE(W42,X42,Y42) -> 4080.225 | AA42: South | AB42: =Table1[[#This Row],[01-01-2025]]+Table1[[#This Row],[01-02-2025]]+Table1[[#This Row],[01-03-2025]]+Table1[[#This Row],[01-04-2025]]+Table1[[#This Row],[01-05-2025]]+Table1[[#This Row],[01-06-2025]] -> 24313.122
A43: 42 | B43: SKU001 | C43: Surf Excel 1kg | D43: South | E43: 6 | F43: 2024 | G43: Jun-2024 | H43: 3458 | I43: 3611 | J43: -153 | K43: 4.4 | L43: E-Commerce | M43: =AVERAGE(H40:H42) -> 3573.6667 | N43: =0.3*H42+(0.7*N42) -> 2850.1608 | O43: =ABS(H43-I43) -> 153 | P43: =ABS(O43)/H43 -> 0.044245228 | Q43: =ABS((H43-N43))/H43 -> 0.17577767 | T43: =C938 -> Close Up 80g | U43: =AVERAGEIFS($H$2:$H$1081,$C$2:$C$1081,$T43,$D$2:$D$1081,$AA43,$F$2:$F$1081,2024,$E$2:$E$1081,">=10") -> 4606.6667 | V43: =AVERAGE(AVERAGEIFS($H$2:$H$1081,$C$2:$C$1081,T43,$D$2:$D$1081,AA43,$F$2:$F$1081,2024,$E$2:$E$1081,"=11"),AVERAGEIFS($H$2:$H$1081,$C$2:$C$1081,T43,$D$2:$D$1081,AA43,$F$2:$F$1081,2024,$E$2:$E$1081,"=12"),U43) -> 4698.2222 | W43: =AVERAGE(AVERAGEIFS($H$2:$H$1081,$C$2:$C$1081,T43,$D$2:$D$1081,AA43,$F$2:$F$1081,2024,$E$2:$E$1081,"=12"),U43,V43) -> 4881.6296 | X43: =AVERAGE(U43,V43,W43) -> 4728.8395 | Y43: =AVERAGE(V43,W43,X43) -> 4769.5638 | Z43: =AVERAGE(W43,X43,Y43) -> 4793.3443 | AA43: West | AB43: =Table1[[#This Row],[01-01-2025]]+Table1[[#This Row],[01-02-2025]]+Table1[[#This Row],[01-03-2025]]+Table1[[#This Row],[01-04-2025]]+Table1[[#This Row],[01-05-2025]]+Table1[[#This Row],[01-06-2025]] -> 28478.266
A44: 43 | B44: SKU001 | C44: Surf Excel 1kg | D44: South | E44: 7 | F44: 2024 | G44: Jul-2024 | H44: 3636 | I44: 3636 | J44: 0 | K44: 0 | L44: Modern Trade | M44: =AVERAGE(H41:H43) -> 3547 | N44: =0.3*H43+(0.7*N43) -> 3032.5126 | O44: =ABS(H44-I44) -> 0 | P44: =ABS(O44)/H44 -> 0 | Q44: =ABS((H44-N44))/H44 -> 0.16597564 | T44: =C1010 -> Kissan Ketchup 500g | U44: =AVERAGEIFS($H$2:$H$1081,$C$2:$C$1081,$T44,$D$2:$D$1081,$AA44,$F$2:$F$1081,2024,$E$2:$E$1081,">=10") -> 972.66667 | V44: =AVERAGE(AVERAGEIFS($H$2:$H$1081,$C$2:$C$1081,T44,$D$2:$D$1081,AA44,$F$2:$F$1081,2024,$E$2:$E$1081,"=11"),AVERAGEIFS($H$2:$H$1081,$C$2:$C$1081,T44,$D$2:$D$1081,AA44,$F$2:$F$1081,2024,$E$2:$E$1081,"=12"),U44) -> 980.88889 | W44: =AVERAGE(AVERAGEIFS($H$2:$H$1081,$C$2:$C$1081,T44,$D$2:$D$1081,AA44,$F$2:$F$1081,2024,$E$2:$E$1081,"=12"),U44,V44) -> 974.51852 | X44: =AVERAGE(U44,V44,W44) -> 976.02469 | Y44: =AVERAGE(V44,W44,X44) -> 977.14403 | Z44: =AVERAGE(W44,X44,Y44) -> 975.89575 | AA44: North | AB44: =Table1[[#This Row],[01-01-2025]]+Table1[[#This Row],[01-02-2025]]+Table1[[#This Row],[01-03-2025]]+Table1[[#This Row],[01-04-2025]]+Table1[[#This Row],[01-05-2025]]+Table1[[#This Row],[01-06-2025]] -> 5857.1385
A45: 44 | B45: SKU001 | C45: Surf Excel 1kg | D45: South | E45: 8 | F45: 2024 | G45: Aug-2024 | H45: 3755 | I45: 3459 | J45: 296 | K45: 7.9 | L45: E-Commerce | M45: =AVERAGE(H42:H44) -> 3497.6667 | N45: =0.3*H44+(0.7*N44) -> 3213.5588 | O45: =ABS(H45-I45) -> 296 | P45: =ABS(O45)/H45 -> 0.078828229 | Q45: =ABS((H45-N45))/H45 -> 0.14419207 | T45: =C1010 -> Kissan Ketchup 500g | U45: =AVERAGEIFS($H$2:$H$1081,$C$2:$C$1081,$T45,$D$2:$D$1081,$AA45,$F$2:$F$1081,2024,$E$2:$E$1081,">=10") -> 810 | V45: =AVERAGE(AVERAGEIFS($H$2:$H$1081,$C$2:$C$1081,T45,$D$2:$D$1081,AA45,$F$2:$F$1081,2024,$E$2:$E$1081,"=11"),AVERAGEIFS($H$2:$H$1081,$C$2:$C$1081,T45,$D$2:$D$1081,AA45,$F$2:$F$1081,2024,$E$2:$E$1081,"=12"),U45) -> 818.66667 | W45: =AVERAGE(AVERAGEIFS($H$2:$H$1081,$C$2:$C$1081,T45,$D$2:$D$1081,AA45,$F$2:$F$1081,2024,$E$2:$E$1081,"=12"),U45,V45) -> 811.55556 | X45: =AVERAGE(U45,V45,W45) -> 813.40741 | Y45: =AVERAGE(V45,W45,X45) -> 814.54321 | Z45: =AVERAGE(W45,X45,Y45) -> 813.16872 | AA45: South | AB45: =Table1[[#This Row],[01-01-2025]]+Table1[[#This Row],[01-02-2025]]+Table1[[#This Row],[01-03-2025]]+Table1[[#This Row],[01-04-2025]]+Table1[[#This Row],[01-05-2025]]+Table1[[#This Row],[01-06-2025]] -> 4881.3416
A46: 45 | B46: SKU001 | C46: Surf Excel 1kg | D46: South | E46: 9 | F46: 2024 | G46: Sep-2024 | H46: 3397 | I46: 3491 | J46: -94 | K46: 2.8 | L46: E-Commerce | M46: =AVERAGE(H43:H45) -> 3616.3333 | N46: =0.3*H45+(0.7*N45) -> 3375.9912 | O46: =ABS(H46-I46) -> 94 | P46: =ABS(O46)/H46 -> 0.027671475 | Q46: =ABS((H46-N46))/H46 -> 0.0061845292 | T46: =C1010 -> Kissan Ketchup 500g | U46: =AVERAGEIFS($H$2:$H$1081,$C$2:$C$1081,$T46,$D$2:$D$1081,$AA46,$F$2:$F$1081,2024,$E$2:$E$1081,">=10") -> 865.33333 | V46: =AVERAGE(AVERAGEIFS($H$2:$H$1081,$C$2:$C$1081,T46,$D$2:$D$1081,AA46,$F$2:$F$1081,2024,$E$2:$E$1081,"=11"),AVERAGEIFS($H$2:$H$1081,$C$2:$C$1081,T46,$D$2:$D$1081,AA46,$F$2:$F$1081,2024,$E$2:$E$1081,"=12"),U46) -> 880.11111 | W46: =AVERAGE(AVERAGEIFS($H$2:$H$1081,$C$2:$C$1081,T46,$D$2:$D$1081,AA46,$F$2:$F$1081,2024,$E$2:$E$1081,"=12"),U46,V46) -> 874.14815 | X46: =AVERAGE(U46,V46,W46) -> 873.19753 | Y46: =AVERAGE(V46,W46,X46) -> 875.81893 | Z46: =AVERAGE(W46,X46,Y46) -> 874.3882 | AA46: West | AB46: =Table1[[#This Row],[01-01-2025]]+Table1[[#This Row],[01-02-2025]]+Table1[[#This Row],[01-03-2025]]+Table1[[#This Row],[01-04-2025]]+Table1[[#This Row],[01-05-2025]]+Table1[[#This Row],[01-06-2025]] -> 5242.9973
A47: 46 | B47: SKU001 | C47: Surf Excel 1kg | D47: South | E47: 10 | F47: 2024 | G47: Oct-2024 | H47: 3643 | I47: 3551 | J47: 92 | K47: 2.5 | L47: Modern Trade | M47: =AVERAGE(H44:H46) -> 3596 | N47: =0.3*H46+(0.7*N46) -> 3382.2938 | O47: =ABS(H47-I47) -> 92 | P47: =ABS(O47)/H47 -> 0.025253912 | Q47: =ABS((H47-N47))/H47 -> 0.071563599
A48: 47 | B48: SKU001 | C48: Surf Excel 1kg | D48: South | E48: 11 | F48: 2024 | G48: Nov-2024 | H48: 4504 | I48: 4754 | J48: -250 | K48: 5.6 | L48: E-Commerce | M48: =AVERAGE(H45:H47) -> 3598.3333 | N48: =0.3*H47+(0.7*N47) -> 3460.5057 | O48: =ABS(H48-I48) -> 250 | P48: =ABS(O48)/H48 -> 0.055506217 | Q48: =ABS((H48-N48))/H48 -> 0.23168169
A49: 48 | B49: SKU001 | C49: Surf Excel 1kg | D49: South | E49: 12 | F49: 2024 | G49: Dec-2024 | H49: 5107 | I49: 5208 | J49: -101 | K49: 2 | L49: General Trade | M49: =AVERAGE(H46:H48) -> 3848 | N49: =0.3*H48+(0.7*N48) -> 3773.554 | O49: =ABS(H49-I49) -> 101 | P49: =ABS(O49)/H49 -> 0.019776777 | Q49: =ABS((H49-N49))/H49 -> 0.26110163
A50: 49 | B50: SKU001 | C50: Surf Excel 1kg | D50: West | E50: 1 | F50: 2023 | G50: Jan-2023 | H50: 3000 | I50: 3257 | J50: -257 | K50: 8.6 | L50: General Trade | M50: =AVERAGE(H47:H49) -> 4418 | N50: =0.3*H49+(0.7*N49) -> 4173.5878 | O50: =ABS(H50-I50) -> 257 | P50: =ABS(O50)/H50 -> 0.085666667 | Q50: =ABS((H50-N50))/H50 -> 0.39119593
A51: 50 | B51: SKU001 | C51: Surf Excel 1kg | D51: West | E51: 2 | F51: 2023 | G51: Feb-2023 | H51: 3067 | I51: 2908 | J51: 159 | K51: 5.2 | L51: E-Commerce | M51: =AVERAGE(H48:H50) -> 4203.6667 | N51: =0.3*H50+(0.7*N50) -> 3821.5114 | O51: =ABS(H51-I51) -> 159 | P51: =ABS(O51)/H51 -> 0.051842191 | Q51: =ABS((H51-N51))/H51 -> 0.2460096
A52: 51 | B52: SKU001 | C52: Surf Excel 1kg | D52: West | E52: 3 | F52: 2023 | G52: Mar-2023 | H52: 4197 | I52: 3849 | J52: 348 | K52: 8.3 | L52: General Trade | M52: =AVERAGE(H49:H51) -> 3724.6667 | N52: =0.3*H51+(0.7*N51) -> 3595.158 | O52: =ABS(H52-I52) -> 348 | P52: =ABS(O52)/H52 -> 0.082916369 | Q52: =ABS((H52-N52))/H52 -> 0.14339814
A53: 52 | B53: SKU001 | C53: Surf Excel 1kg | D53: West | E53: 4 | F53: 2023 | G53: Apr-2023 | H53: 4292 | I53: 4702 | J53: -410 | K53: 9.6 | L53: E-Commerce | M53: =AVERAGE(H50:H52) -> 3421.3333 | N53: =0.3*H52+(0.7*N52) -> 3775.7106 | O53: =ABS(H53-I53) -> 410 | P53: =ABS(O53)/H53 -> 0.095526561 | Q53: =ABS((H53-N53))/H53 -> 0.1202911
A54: 53 | B54: SKU001 | C54: Surf Excel 1kg | D54: West | E54: 5 | F54: 2023 | G54: May-2023 | H54: 4456 | I54: 4124 | J54: 332 | K54: 7.5 | L54: General Trade | M54: =AVERAGE(H51:H53) -> 3852 | N54: =0.3*H53+(0.7*N53) -> 3930.5974 | O54: =ABS(H54-I54) -> 332 | P54: =ABS(O54)/H54 -> 0.074506284 | Q54: =ABS((H54-N54))/H54 -> 0.11790902
A55: 54 | B55: SKU001 | C55: Surf Excel 1kg | D55: West | E55: 6 | F55: 2023 | G55: Jun-2023 | H55: 4859 | I55: 4533 | J55: 326 | K55: 6.7 | L55: E-Commerce | M55: =AVERAGE(H52:H54) -> 4315 | N55: =0.3*H54+(0.7*N54) -> 4088.2182 | O55: =ABS(H55-I55) -> 326 | P55: =ABS(O55)/H55 -> 0.067091994 | Q55: =ABS((H55-N55))/H55 -> 0.15862972
A56: 55 | B56: SKU001 | C56: Surf Excel 1kg | D56: West | E56: 7 | F56: 2023 | G56: Jul-2023 | H56: 4694 | I56: 4621 | J56: 73 | K56: 1.6 | L56: Modern Trade | M56: =AVERAGE(H53:H55) -> 4535.6667 | N56: =0.3*H55+(0.7*N55) -> 4319.4527 | O56: =ABS(H56-I56) -> 73 | P56: =ABS(O56)/H56 -> 0.015551768 | Q56: =ABS((H56-N56))/H56 -> 0.07979277
A57: 56 | B57: SKU001 | C57: Surf Excel 1kg | D57: West | E57: 8 | F57: 2023 | G57: Aug-2023 | H57: 4620 | I57: 4855 | J57: -235 | K57: 5.1 | L57: E-Commerce | M57: =AVERAGE(H54:H56) -> 4669.6667 | N57: =0.3*H56+(0.7*N56) -> 4431.8169 | O57: =ABS(H57-I57) -> 235 | P57: =ABS(O57)/H57 -> 0.050865801 | Q57: =ABS((H57-N57))/H57 -> 0.040732269
A58: 57 | B58: SKU001 | C58: Surf Excel 1kg | D58: West | E58: 9 | F58: 2023 | G58: Sep-2023 | H58: 3703 | I58: 3563 | J58: 140 | K58: 3.8 | L58: E-Commerce | M58: =AVERAGE(H55:H57) -> 4724.3333 | N58: =0.3*H57+(0.7*N57) -> 4488.2718 | O58: =ABS(H58-I58) -> 140 | P58: =ABS(O58)/H58 -> 0.037807183 | Q58: =ABS((H58-N58))/H58 -> 0.21206369
... A1081: 1080 | B1081: SKU015 | C1081: Kissan Ketchup 500g | D1081: West | E1081: 12 | F1081: 2024 | G1081: Dec-2024 | H1081: 877 | I1081: 897 | J1081: -20 | K1081: 2.3 | L1081: Modern Trade | M1081: =AVERAGE(H1078:H1080) -> 819.66667 | N1081: =0.3*H1080+(0.7*N1080) -> 807.47744 | O1081: =ABS(H1081-I1081) -> 20 | P1081: =ABS(O1081)/H1081 -> 0.022805017 | Q1081: =ABS((H1081-N1081))/H1081 -> 0.079273156
M1082: =AVERAGE(H1079:H1081) -> 865.33333
M1083: =AVERAGE(H1080:H1082) -> 887.5
M1084: =AVERAGE(H1081:H1083) -> 877

Sheet Inventory_Snapshot
A1: SKU_ID | B1: Product_Name | C1: Warehouse | D1: Opening_Stock | E1: Receipts | F1: Dispatches | G1: Closing_Stock | H1: Stock_Status | L1: EOQ | M1: Safety Stock | N1: Reorder Point | O1: Days of Cover | P1: Stock Status flag
A2: SKU001 | B2: Surf Excel 1kg | C2: Delhi WH | D2: 4719 | E2: 3147 | F2: 4373 | G2: 3493 | H2: OK | L2: =VLOOKUP(Table3[[#This Row],[SKU_ID]],Table2[],16,0) -> 2923.2637 | M2: =VLOOKUP(Table3[[#This Row],[SKU_ID]],Table2[],18,0) -> 1321.742 | N2: =VLOOKUP(Table3[[#This Row],[SKU_ID]],Table2[],19,0) -> 6893.8571 | O2: =VLOOKUP(Table3[[#This Row],[SKU_ID]],Table2[],20,0) -> 8.7762007 | P2: =IF(Table3[[#This Row],[Closing_Stock]]<Table7[[#This Row],[Safety Stock]],"Critical",IF(G2<Table7[[#This Row],[Reorder Point]],"ReOrder","OK")) -> ReOrder
A3: SKU001 | B3: Surf Excel 1kg | C3: Mumbai WH | D3: 4147 | E3: 2170 | F3: 3158 | G3: 3159 | H3: OK | L3: =VLOOKUP(Table3[[#This Row],[SKU_ID]],Table2[],16,0) -> 2923.2637 | M3: =VLOOKUP(Table3[[#This Row],[SKU_ID]],Table2[],18,0) -> 1321.742 | N3: =VLOOKUP(Table3[[#This Row],[SKU_ID]],Table2[],19,0) -> 6893.8571 | O3: =VLOOKUP(Table3[[#This Row],[SKU_ID]],Table2[],20,0) -> 8.7762007 | P3: =IF(Table3[[#This Row],[Closing_Stock]]<Table7[[#This Row],[Safety Stock]],"Critical",IF(G3<Table7[[#This Row],[Reorder Point]],"ReOrder","OK")) -> ReOrder
A4: SKU001 | B4: Surf Excel 1kg | C4: Bangalore WH | D4: 3731 | E4: 3035 | F4: 3690 | G4: 3076 | H4: OK | L4: =VLOOKUP(Table3[[#This Row],[SKU_ID]],Table2[],16,0) -> 2923.2637 | M4: =VLOOKUP(Table3[[#This Row],[SKU_ID]],Table2[],18,0) -> 1321.742 | N4: =VLOOKUP(Table3[[#This Row],[SKU_ID]],Table2[],19,0) -> 6893.8571 | O4: =VLOOKUP(Table3[[#This Row],[SKU_ID]],Table2[],20,0) -> 8.7762007 | P4: =IF(Table3[[#This Row],[Closing_Stock]]<Table7[[#This Row],[Safety Stock]],"Critical",IF(G4<Table7[[#This Row],[Reorder Point]],"ReOrder","OK")) -> ReOrder
A5: SKU002 | B5: Surf Excel 500g | C5: Delhi WH | D5: 6287 | E5: 6779 | F5: 5928 | G5: 7138 | H5: OK | L5: =VLOOKUP(Table3[[#This Row],[SKU_ID]],Table2[],16,0) -> 5143.9825 | M5: =VLOOKUP(Table3[[#This Row],[SKU_ID]],Table2[],18,0) -> 1322.3094 | N5: =VLOOKUP(Table3[[#This Row],[SKU_ID]],Table2[],19,0) -> 10456.638 | O5: =VLOOKUP(Table3[[#This Row],[SKU_ID]],Table2[],20,0) -> 4.8417351 | P5: =IF(Table3[[#This Row],[Closing_Stock]]<Table7[[#This Row],[Safety Stock]],"Critical",IF(G5<Table7[[#This Row],[Reorder Point]],"ReOrder","OK")) -> ReOrder
A6: SKU002 | B6: Surf Excel 500g | C6: Mumbai WH | D6: 5231 | E6: 4465 | F6: 6180 | G6: 3516 | H6: OK | L6: =VLOOKUP(Table3[[#This Row],[SKU_ID]],Table2[],16,0) -> 5143.9825 | M6: =VLOOKUP(Table3[[#This Row],[SKU_ID]],Table2[],18,0) -> 1322.3094 | N6: =VLOOKUP(Table3[[#This Row],[SKU_ID]],Table2[],19,0) -> 10456.638 | O6: =VLOOKUP(Table3[[#This Row],[SKU_ID]],Table2[],20,0) -> 4.8417351 | P6: =IF(Table3[[#This Row],[Closing_Stock]]<Table7[[#This Row],[Safety Stock]],"Critical",IF(G6<Table7[[#This Row],[Reorder Point]],"ReOrder","OK")) -> ReOrder
A7: SKU002 | B7: Surf Excel 500g | C7: Bangalore WH | D7: 6222 | E7: 5330 | F7: 4619 | G7: 6933 | H7: OK | L7: =VLOOKUP(Table3[[#This Row],[SKU_ID]],Table2[],16,0) -> 5143.9825 | M7: =VLOOKUP(Table3[[#This Row],[SKU_ID]],Table2[],18,0) -> 1322.3094 | N7: =VLOOKUP(Table3[[#This Row],[SKU_ID]],Table2[],19,0) -> 10456.638 | O7: =VLOOKUP(Table3[[#This Row],[SKU_ID]],Table2[],20,0) -> 4.8417351 | P7: =IF(Table3[[#This Row],[Closing_Stock]]<Table7[[#This Row],[Safety Stock]],"Critical",IF(G7<Table7[[#This Row],[Reorder Point]],"ReOrder","OK")) -> ReOrder
A8: SKU003 | B8: Vim Bar 200g | C8: Delhi WH | D8: 10286 | E8: 6277 | F8: 6984 | G8: 9579 | H8: OK | L8: =VLOOKUP(Table3[[#This Row],[SKU_ID]],Table2[],16,0) -> 9674.7954 | M8: =VLOOKUP(Table3[[#This Row],[SKU_ID]],Table2[],18,0) -> 944.8728 | N8: =VLOOKUP(Table3[[#This Row],[SKU_ID]],Table2[],19,0) -> 10176.818 | O8: =VLOOKUP(Table3[[#This Row],[SKU_ID]],Table2[],20,0) -> 3.3319089 | P8: =IF(Table3[[#This Row],[Closing_Stock]]<Table7[[#This Row],[Safety Stock]],"Critical",IF(G8<Table7[[#This Row],[Reorder Point]],"ReOrder","OK")) -> ReOrder
A9: SKU003 | B9: Vim Bar 200g | C9: Mumbai WH | D9: 7337 | E9: 7206 | F9: 5547 | G9: 8996 | H9: OK | L9: =VLOOKUP(Table3[[#This Row],[SKU_ID]],Table2[],16,0) -> 9674.7954 | M9: =VLOOKUP(Table3[[#This Row],[SKU_ID]],Table2[],18,0) -> 944.8728 | N9: =VLOOKUP(Table3[[#This Row],[SKU_ID]],Table2[],19,0) -> 10176.818 | O9: =VLOOKUP(Table3[[#This Row],[SKU_ID]],Table2[],20,0) -> 3.3319089 | P9: =IF(Table3[[#This Row],[Closing_Stock]]<Table7[[#This Row],[Safety Stock]],"Critical",IF(G9<Table7[[#This Row],[Reorder Point]],"ReOrder","OK")) -> ReOrder
A10: SKU003 | B10: Vim Bar 200g | C10: Bangalore WH | D10: 10076 | E10: 5354 | F10: 8396 | G10: 7034 | H10: OK | L10: =VLOOKUP(Table3[[#This Row],[SKU_ID]],Table2[],16,0) -> 9674.7954 | M10: =VLOOKUP(Table3[[#This Row],[SKU_ID]],Table2[],18,0) -> 944.8728 | N10: =VLOOKUP(Table3[[#This Row],[SKU_ID]],Table2[],19,0) -> 10176.818 | O10: =VLOOKUP(Table3[[#This Row],[SKU_ID]],Table2[],20,0) -> 3.3319089 | P10: =IF(Table3[[#This Row],[Closing_Stock]]<Table7[[#This Row],[Safety Stock]],"Critical",IF(G10<Table7[[#This Row],[Reorder Point]],"ReOrder","OK")) -> ReOrder
A11: SKU004 | B11: Vim Liquid 500ml | C11: Delhi WH | D11: 3314 | E11: 2171 | F11: 2854 | G11: 2631 | H11: OK | L11: =VLOOKUP(Table3[[#This Row],[SKU_ID]],Table2[],16,0) -> 3184.1654 | M11: =VLOOKUP(Table3[[#This Row],[SKU_ID]],Table2[],18,0) -> 945.30385 | N11: =VLOOKUP(Table3[[#This Row],[SKU_ID]],Table2[],19,0) -> 4000.8655 | O11: =VLOOKUP(Table3[[#This Row],[SKU_ID]],Table2[],20,0) -> 23.360681 | P11: =IF(Table3[[#This Row],[Closing_Stock]]<Table7[[#This Row],[Safety Stock]],"Critical",IF(G11<Table7[[#This Row],[Reorder Point]],"ReOrder","OK")) -> ReOrder
A12: SKU004 | B12: Vim Liquid 500ml | C12: Mumbai WH | D12: 2785 | E12: 1762 | F12: 2200 | G12: 2347 | H12: OK | L12: =VLOOKUP(Table3[[#This Row],[SKU_ID]],Table2[],16,0) -> 3184.1654 | M12: =VLOOKUP(Table3[[#This Row],[SKU_ID]],Table2[],18,0) -> 945.30385 | N12: =VLOOKUP(Table3[[#This Row],[SKU_ID]],Table2[],19,0) -> 4000.8655 | O12: =VLOOKUP(Table3[[#This Row],[SKU_ID]],Table2[],20,0) -> 23.360681 | P12: =IF(Table3[[#This Row],[Closing_Stock]]<Table7[[#This Row],[Safety Stock]],"Critical",IF(G12<Table7[[#This Row],[Reorder Point]],"ReOrder","OK")) -> ReOrder
A13: SKU004 | B13: Vim Liquid 500ml | C13: Bangalore WH | D13: 2592 | E13: 2159 | F13: 2803 | G13: 1948 | H13: OK | L13: =VLOOKUP(Table3[[#This Row],[SKU_ID]],Table2[],16,0) -> 3184.1654 | M13: =VLOOKUP(Table3[[#This Row],[SKU_ID]],Table2[],18,0) -> 945.30385 | N13: =VLOOKUP(Table3[[#This Row],[SKU_ID]],Table2[],19,0) -> 4000.8655 | O13: =VLOOKUP(Table3[[#This Row],[SKU_ID]],Table2[],20,0) -> 23.360681 | P13: =IF(Table3[[#This Row],[Closing_Stock]]<Table7[[#This Row],[Safety Stock]],"Critical",IF(G13<Table7[[#This Row],[Reorder Point]],"ReOrder","OK")) -> ReOrder
... A46: SKU015 | B46: Kissan Ketchup 500g | C46: Bangalore WH | D46: 717 | E46: 499 | F46: 480 | G46: 736 | H46: OK | L46: =VLOOKUP(Table3[[#This Row],[SKU_ID]],Table2[],16,0) -> 1328.919 | M46: =VLOOKUP(Table3[[#This Row],[SKU_ID]],Table2[],18,0) -> 1994.9585 | N46: =VLOOKUP(Table3[[#This Row],[SKU_ID]],Table2[],19,0) -> 3580.027 | O46: =VLOOKUP(Table3[[#This Row],[SKU_ID]],Table2[],20,0) -> 220.55009 | P46: =IF(Table3[[#This Row],[Closing_Stock]]<Table7[[#This Row],[Safety Stock]],"Critical",IF(G46<Table7[[#This Row],[Reorder Point]],"ReOrder","OK")) -> Critical

Sheet Supplier_Master
A1: Supplier_ID | B1: Supplier_Name | C1: Category | D1: Location | E1: Contact_Person | F1: Lead_Time_(Days) | G1: Payment_Terms | H1: Min_Order_Value_(INR) | I1: On_Time_Delivery_(%) | J1: Quality_Rejection_(%) | K1: Preferred
A2: SUP001 | B2: Hindustan Unilever Ltd | C2: Detergent / Personal Care | D2: Mumbai | E2: Ramesh Kumar | F2: 14 | G2: Net 30 | H2: 50000 | I2: 96.2 | J2: 0.8 | K2: Yes
A3: SUP002 | B3: Procter & Gamble | C3: Personal Care | D3: Mumbai | E3: Sneha Iyer | F3: 21 | G3: Net 45 | H3: 75000 | I3: 94.5 | J3: 1.2 | K3: Yes
A4: SUP003 | B4: Reckitt Benckiser | C4: Health & Hygiene | D4: Gurgaon | E4: Ajay Sharma | F4: 10 | G4: Net 30 | H4: 40000 | I4: 97.1 | J4: 0.5 | K4: Yes
A5: SUP004 | B5: Godrej Consumer | C5: Personal Care | D5: Mumbai | E5: Priya Mehta | F5: 7 | G5: Net 30 | H5: 30000 | I5: 95.8 | J5: 0.9 | K5: Yes
A6: SUP005 | B6: Marico Ltd | C6: Hair Care | D6: Mumbai | E6: Vivek Nair | F6: 14 | G6: Net 45 | H6: 35000 | I6: 93.2 | J6: 1.5 | K6: No
A7: SUP006 | B7: Dabur India | C7: Oral / Health | D7: Delhi | E7: Sunita Rao | F7: 10 | G7: Net 30 | H7: 25000 | I7: 96.7 | J7: 0.6 | K7: Yes
A8: SUP007 | B8: Emami Ltd | C8: Skincare | D8: Kolkata | E8: Anil Gupta | F8: 14 | G8: Net 45 | H8: 20000 | I8: 91.5 | J8: 2.1 | K8: No
A9: SUP008 | B9: ITC Ltd | C9: Food | D9: Kolkata | E9: Deepak Joshi | F9: 21 | G9: Net 60 | H9: 60000 | I9: 94 | J9: 1 | K9: Yes
A10: SUP009 | B10: Nestle India | C10: Food | D10: Pune | E10: Kavita Singh | F10: 21 | G10: Net 45 | H10: 80000 | I10: 95.5 | J10: 0.7 | K10: Yes
A11: SUP010 | B11: Wipro Consumer | C11: Lighting / Consumer | D11: Bangalore | E11: Rohit Das | F11: 14 | G11: Net 30 | H11: 45000 | I11: 92.8 | J11: 1.8 | K11: No

Sheet Purchase_Orders
A1: PO_Number | B1: SKU_ID | C1: Product_Name | D1: Supplier_ID | E1: Supplier_Name | F1: PO_Date | G1: Expected_Delivery | H1: Actual_Delivery | I1: Qty_Ordered | J1: Qty_Received | K1: Unit_Cost_(INR) | L1: PO_Value_(INR) | M1: Status | N1: Remarks
A2: PO-2024-0001 | B2: SKU001 | C2: Surf Excel 1kg | D2: SUP001 | E2: Hindustan Unilever Ltd | F2: 14-Sep-2024 | G2: 28-Sep-2024 | H2: - | I2: 3161 | J2: 0 | K2: 85 | L2: 268685 | M2: In Transit | N2: -
A3: PO-2024-0002 | B3: SKU001 | C3: Surf Excel 1kg | D3: SUP001 | E3: Hindustan Unilever Ltd | F3: 29-Aug-2024 | G3: 12-Sep-2024 | H3: - | I3: 2310 | J3: 0 | K3: 85 | L3: 196350 | M3: Pending | N3: -
A4: PO-2024-0003 | B4: SKU001 | C4: Surf Excel 1kg | D4: SUP001 | E4: Hindustan Unilever Ltd | F4: 01-Oct-2024 | G4: 15-Oct-2024 | H4: - | I4: 2773 | J4: 0 | K4: 85 | L4: 235705 | M4: Pending | N4: -
A5: PO-2024-0004 | B5: SKU001 | C5: Surf Excel 1kg | D5: SUP001 | E5: Hindustan Unilever Ltd | F5: 23-Nov-2024 | G5: 07-Dec-2024 | H5: 07-Dec-2024 | I5: 2438 | J5: 2438 | K5: 85 | L5: 207230 | M5: Delivered | N5: On time
A6: PO-2024-0005 | B6: SKU002 | C6: Surf Excel 500g | D6: SUP001 | E6: Hindustan Unilever Ltd | F6: 09-Jun-2024 | G6: 23-Jun-2024 | H6: 21-Jun-2024 | I6: 3586 | J6: 3586 | K6: 45 | L6: 161370 | M6: Delivered | N6: On time
A7: PO-2024-0006 | B7: SKU002 | C7: Surf Excel 500g | D7: SUP001 | E7: Hindustan Unilever Ltd | F7: 27-Jun-2024 | G7: 11-Jul-2024 | H7: 14-Jul-2024 | I7: 3182 | J7: 3182 | K7: 45 | L7: 143190 | M7: Delivered | N7: Delayed
A8: PO-2024-0007 | B8: SKU002 | C8: Surf Excel 500g | D8: SUP001 | E8: Hindustan Unilever Ltd | F8: 05-Sep-2024 | G8: 19-Sep-2024 | H8: 18-Sep-2024 | I8: 4207 | J8: 4207 | K8: 45 | L8: 189315 | M8: Delivered | N8: On time
A9: PO-2024-0008 | B9: SKU002 | C9: Surf Excel 500g | D9: SUP001 | E9: Hindustan Unilever Ltd | F9: 24-Jun-2024 | G9: 08-Jul-2024 | H9: 13-Jul-2024 | I9: 4636 | J9: 4636 | K9: 45 | L9: 208620 | M9: Delivered | N9: Delayed
A10: PO-2024-0009 | B10: SKU003 | C10: Vim Bar 200g | D10: SUP003 | E10: Reckitt Benckiser | F10: 19-Sep-2024 | G10: 03-Oct-2024 | H10: 07-Oct-2024 | I10: 4396 | J10: 4396 | K10: 18 | L10: 79128 | M10: Delivered | N10: Delayed
A11: PO-2024-0010 | B11: SKU003 | C11: Vim Bar 200g | D11: SUP003 | E11: Reckitt Benckiser | F11: 26-Jun-2024 | G11: 10-Jul-2024 | H11: 11-Jul-2024 | I11: 7502 | J11: 7502 | K11: 18 | L11: 135036 | M11: Delivered | N11: Delayed
A12: PO-2024-0011 | B12: SKU003 | C12: Vim Bar 200g | D12: SUP003 | E12: Reckitt Benckiser | F12: 13-Sep-2024 | G12: 27-Sep-2024 | H12: - | I12: 6543 | J12: 0 | K12: 18 | L12: 117774 | M12: Pending | N12: -
A13: PO-2024-0012 | B13: SKU003 | C13: Vim Bar 200g | D13: SUP003 | E13: Reckitt Benckiser | F13: 17-Oct-2024 | G13: 31-Oct-2024 | H13: 02-Nov-2024 | I13: 4930 | J13: 4930 | K13: 18 | L13: 88740 | M13: Delivered | N13: Delayed
... A61: PO-2024-0060 | B61: SKU015 | C61: Kissan Ketchup 500g | D61: SUP008 | E61: ITC Ltd | F61: 10-Nov-2024 | G61: 24-Nov-2024 | H61: 22-Nov-2024 | I61: 397 | J61: 397 | K61: 78 | L61: 30966 | M61: Delivered | N61: On time

Sheet Bull whip 
A1: SKU | B1: Mean Demand | C1: StDev Demand | D1: CV Demand | E1: Mean Orders | F1: StDev Orders | G1: CV Orders | H1: Bullwhip Ratio | I1: Interpretation
A2: =Table2[[#This Row],[SKU_ID]] -> SKU001 | B2: =AVERAGEIF(Demand_Data!B2:B1081,Table5[[#This Row],[SKU]],Demand_Data!H2:H1081) -> 4075.7183 | C2: {=STDEV(IF(Demand_Data!B2:B1081=Table5[[#This Row],[SKU]],Demand_Data!H2:H1081))} -> 646.1736 | D2: =Table5[[#This Row],[StDev Demand]]/Table5[[#This Row],[Mean Demand]] -> 0.15854226 | E2: =AVERAGEIFS(Purchase_Orders!I2:I61,Purchase_Orders!B2:B61,Table5[[#This Row],[SKU]]) -> 2670.5 | F2: {=STDEV(IF(Purchase_Orders!B2:B61=Table5[[#This Row],[SKU]],Purchase_Orders!I2:I61))} -> 380.83811 | G2: =Table5[[#This Row],[ StDev Orders]]/Table5[[#This Row],[ Mean Orders ]] -> 0.14260929 | H2: =Table5[[#This Row],[CV Orders]]/Table5[[#This Row],[ CV Demand ]] -> 0.89950332 | I2: =IF(Table5[[#This Row],[Bullwhip Ratio]]>1.5,"High Bullwhip",IF(Table5[[#This Row],[Bullwhip Ratio]]>1,"Moderate Bullwhip","Stable")) -> Stable
A3: =Table2[[#This Row],[SKU_ID]] -> SKU002 | B3: =AVERAGEIF(Demand_Data!B3:B1082,Table5[[#This Row],[SKU]],Demand_Data!H3:H1082) -> 6624.5833 | C3: {=STDEV(IF(Demand_Data!B3:B1082=Table5[[#This Row],[SKU]],Demand_Data!H3:H1082))} -> 1095.8276 | D3: =Table5[[#This Row],[StDev Demand]]/Table5[[#This Row],[Mean Demand]] -> 0.16541834 | E3: =AVERAGEIFS(Purchase_Orders!I3:I62,Purchase_Orders!B3:B62,Table5[[#This Row],[SKU]]) -> 3902.75 | F3: {=STDEV(IF(Purchase_Orders!B3:B62=Table5[[#This Row],[SKU]],Purchase_Orders!I3:I62))} -> 645.5062 | G3: =Table5[[#This Row],[ StDev Orders]]/Table5[[#This Row],[ Mean Orders ]] -> 0.16539778 | H3: =Table5[[#This Row],[CV Orders]]/Table5[[#This Row],[ CV Demand ]] -> 0.99987572 | I3: =IF(Table5[[#This Row],[Bullwhip Ratio]]>1.5,"High Bullwhip",IF(Table5[[#This Row],[Bullwhip Ratio]]>1,"Moderate Bullwhip","Stable")) -> Stable
A4: =Table2[[#This Row],[SKU_ID]] -> SKU003 | B4: =AVERAGEIF(Demand_Data!B4:B1083,Table5[[#This Row],[SKU]],Demand_Data!H4:H1083) -> 9268.4028 | C4: {=STDEV(IF(Demand_Data!B4:B1083=Table5[[#This Row],[SKU]],Demand_Data!H4:H1083))} -> 1573.2624 | D4: =Table5[[#This Row],[StDev Demand]]/Table5[[#This Row],[Mean Demand]] -> 0.16974472 | E4: =AVERAGEIFS(Purchase_Orders!I4:I63,Purchase_Orders!B4:B63,Table5[[#This Row],[SKU]]) -> 5842.75 | F4: {=STDEV(IF(Purchase_Orders!B4:B63=Table5[[#This Row],[SKU]],Purchase_Orders!I4:I63))} -> 1434.0687 | G4: =Table5[[#This Row],[ StDev Orders]]/Table5[[#This Row],[ Mean Orders ]] -> 0.24544412 | H4: =Table5[[#This Row],[CV Orders]]/Table5[[#This Row],[ CV Demand ]] -> 1.4459603 | I4: =IF(Table5[[#This Row],[Bullwhip Ratio]]>1.5,"High Bullwhip",IF(Table5[[#This Row],[Bullwhip Ratio]]>1,"Moderate Bullwhip","Stable")) -> Moderate Bullwhip
A5: =Table2[[#This Row],[SKU_ID]] -> SKU004 | B5: =AVERAGEIF(Demand_Data!B5:B1084,Table5[[#This Row],[SKU]],Demand_Data!H5:H1084) -> 3098.5 | C5: {=STDEV(IF(Demand_Data!B5:B1084=Table5[[#This Row],[SKU]],Demand_Data!H5:H1084))} -> 516.62115 | D5: =Table5[[#This Row],[StDev Demand]]/Table5[[#This Row],[Mean Demand]] -> 0.16673266 | E5: =AVERAGEIFS(Purchase_Orders!I5:I64,Purchase_Orders!B5:B64,Table5[[#This Row],[SKU]]) -> 1995 | F5: {=STDEV(IF(Purchase_Orders!B5:B64=Table5[[#This Row],[SKU]],Purchase_Orders!I5:I64))} -> 251.59094 | G5: =Table5[[#This Row],[ StDev Orders]]/Table5[[#This Row],[ Mean Orders ]] -> 0.12611075 | H5: =Table5[[#This Row],[CV Orders]]/Table5[[#This Row],[ CV Demand ]] -> 0.75636499 | I5: =IF(Table5[[#This Row],[Bullwhip Ratio]]>1.5,"High Bullwhip",IF(Table5[[#This Row],[Bullwhip Ratio]]>1,"Moderate Bullwhip","Stable")) -> Stable
A6: =Table2[[#This Row],[SKU_ID]] -> SKU005 | B6: =AVERAGEIF(Demand_Data!B6:B1085,Table5[[#This Row],[SKU]],Demand_Data!H6:H1085) -> 11856.847 | C6: {=STDEV(IF(Demand_Data!B6:B1085=Table5[[#This Row],[SKU]],Demand_Data!H6:H1085))} -> 1808.7668 | D6: =Table5[[#This Row],[StDev Demand]]/Table5[[#This Row],[Mean Demand]] -> 0.1525504 | E6: =AVERAGEIFS(Purchase_Orders!I6:I65,Purchase_Orders!B6:B65,Table5[[#This Row],[SKU]]) -> 7352.25 | F6: {=STDEV(IF(Purchase_Orders!B6:B65=Table5[[#This Row],[SKU]],Purchase_Orders!I6:I65))} -> 1367.6428 | G6: =Table5[[#This Row],[ StDev Orders]]/Table5[[#This Row],[ Mean Orders ]] -> 0.18601691 | H6: =Table5[[#This Row],[CV Orders]]/Table5[[#This Row],[ CV Demand ]] -> 1.21938 | I6: =IF(Table5[[#This Row],[Bullwhip Ratio]]>1.5,"High Bullwhip",IF(Table5[[#This Row],[Bullwhip Ratio]]>1,"Moderate Bullwhip","Stable")) -> Moderate Bullwhip
A7: =Table2[[#This Row],[SKU_ID]] -> SKU006 | B7: =AVERAGEIF(Demand_Data!B7:B1086,Table5[[#This Row],[SKU]],Demand_Data!H7:H1086) -> 10686.736 | C7: {=STDEV(IF(Demand_Data!B7:B1086=Table5[[#This Row],[SKU]],Demand_Data!H7:H1086))} -> 1877.5734 | D7: =Table5[[#This Row],[StDev Demand]]/Table5[[#This Row],[Mean Demand]] -> 0.17569194 | E7: =AVERAGEIFS(Purchase_Orders!I7:I66,Purchase_Orders!B7:B66,Table5[[#This Row],[SKU]]) -> 5780.25 | F7: {=STDEV(IF(Purchase_Orders!B7:B66=Table5[[#This Row],[SKU]],Purchase_Orders!I7:I66))} -> 1733.1356 | G7: =Table5[[#This Row],[ StDev Orders]]/Table5[[#This Row],[ Mean Orders ]] -> 0.29983748 | H7: =Table5[[#This Row],[CV Orders]]/Table5[[#This Row],[ CV Demand ]] -> 1.7066092 | I7: =IF(Table5[[#This Row],[Bullwhip Ratio]]>1.5,"High Bullwhip",IF(Table5[[#This Row],[Bullwhip Ratio]]>1,"Moderate Bullwhip","Stable")) -> High Bullwhip
A8: =Table2[[#This Row],[SKU_ID]] -> SKU007 | B8: =AVERAGEIF(Demand_Data!B8:B1087,Table5[[#This Row],[SKU]],Demand_Data!H8:H1087) -> 1747.125 | C8: {=STDEV(IF(Demand_Data!B8:B1087=Table5[[#This Row],[SKU]],Demand_Data!H8:H1087))} -> 277.63478 | D8: =Table5[[#This Row],[StDev Demand]]/Table5[[#This Row],[Mean Demand]] -> 0.15890951 | E8: =AVERAGEIFS(Purchase_Orders!I8:I67,Purchase_Orders!B8:B67,Table5[[#This Row],[SKU]]) -> 1339.75 | F8: {=STDEV(IF(Purchase_Orders!B8:B67=Table5[[#This Row],[SKU]],Purchase_Orders!I8:I67))} -> 102.06983 | G8: =Table5[[#This Row],[ StDev Orders]]/Table5[[#This Row],[ Mean Orders ]] -> 0.076185728 | H8: =Table5[[#This Row],[CV Orders]]/Table5[[#This Row],[ CV Demand ]] -> 0.47942838 | I8: =IF(Table5[[#This Row],[Bullwhip Ratio]]>1.5,"High Bullwhip",IF(Table5[[#This Row],[Bullwhip Ratio]]>1,"Moderate Bullwhip","Stable")) -> Stable
A9: =Table2[[#This Row],[SKU_ID]] -> SKU008 | B9: =AVERAGEIF(Demand_Data!B9:B1088,Table5[[#This Row],[SKU]],Demand_Data!H9:H1088) -> 2125.5139 | C9: {=STDEV(IF(Demand_Data!B9:B1088=Table5[[#This Row],[SKU]],Demand_Data!H9:H1088))} -> 357.00381 | D9: =Table5[[#This Row],[StDev Demand]]/Table5[[#This Row],[Mean Demand]] -> 0.16796117 | E9: =AVERAGEIFS(Purchase_Orders!I9:I68,Purchase_Orders!B9:B68,Table5[[#This Row],[SKU]]) -> 1311.25 | F9: {=STDEV(IF(Purchase_Orders!B9:B68=Table5[[#This Row],[SKU]],Purchase_Orders!I9:I68))} -> 326.4949 | G9: =Table5[[#This Row],[ StDev Orders]]/Table5[[#This Row],[ Mean Orders ]] -> 0.24899515 | H9: =Table5[[#This Row],[CV Orders]]/Table5[[#This Row],[ CV Demand ]] -> 1.4824566 | I9: =IF(Table5[[#This Row],[Bullwhip Ratio]]>1.5,"High Bullwhip",IF(Table5[[#This Row],[Bullwhip Ratio]]>1,"Moderate Bullwhip","Stable")) -> Moderate Bullwhip
A10: =Table2[[#This Row],[SKU_ID]] -> SKU009 | B10: =AVERAGEIF(Demand_Data!B10:B1089,Table5[[#This Row],[SKU]],Demand_Data!H10:H1089) -> 2706.4167 | C10: {=STDEV(IF(Demand_Data!B10:B1089=Table5[[#This Row],[SKU]],Demand_Data!H10:H1089))} -> 439.55627 | D10: =Table5[[#This Row],[StDev Demand]]/Table5[[#This Row],[Mean Demand]] -> 0.16241264 | E10: =AVERAGEIFS(Purchase_Orders!I10:I69,Purchase_Orders!B10:B69,Table5[[#This Row],[SKU]]) -> 1540.25 | F10: {=STDEV(IF(Purchase_Orders!B10:B69=Table5[[#This Row],[SKU]],Purchase_Orders!I10:I69))} -> 168.92281 | G10: =Table5[[#This Row],[ StDev Orders]]/Table5[[#This Row],[ Mean Orders ]] -> 0.10967233 | H10: =Table5[[#This Row],[CV Orders]]/Table5[[#This Row],[ CV Demand ]] -> 0.67526971 | I10: =IF(Table5[[#This Row],[Bullwhip Ratio]]>1.5,"High Bullwhip",IF(Table5[[#This Row],[Bullwhip Ratio]]>1,"Moderate Bullwhip","Stable")) -> Stable
A11: =Table2[[#This Row],[SKU_ID]] -> SKU010 | B11: =AVERAGEIF(Demand_Data!B11:B1090,Table5[[#This Row],[SKU]],Demand_Data!H11:H1090) -> 3469.6389 | C11: {=STDEV(IF(Demand_Data!B11:B1090=Table5[[#This Row],[SKU]],Demand_Data!H11:H1090))} -> 575.82578 | D11: =Table5[[#This Row],[StDev Demand]]/Table5[[#This Row],[Mean Demand]] -> 0.1659613 | E11: =AVERAGEIFS(Purchase_Orders!I11:I70,Purchase_Orders!B11:B70,Table5[[#This Row],[SKU]]) -> 2043.25 | F11: {=STDEV(IF(Purchase_Orders!B11:B70=Table5[[#This Row],[SKU]],Purchase_Orders!I11:I70))} -> 292.70961 | G11: =Table5[[#This Row],[ StDev Orders]]/Table5[[#This Row],[ Mean Orders ]] -> 0.14325688 | H11: =Table5[[#This Row],[CV Orders]]/Table5[[#This Row],[ CV Demand ]] -> 0.86319446 | I11: =IF(Table5[[#This Row],[Bullwhip Ratio]]>1.5,"High Bullwhip",IF(Table5[[#This Row],[Bullwhip Ratio]]>1,"Moderate Bullwhip","Stable")) -> Stable
A12: =Table2[[#This Row],[SKU_ID]] -> SKU011 | B12: =AVERAGEIF(Demand_Data!B12:B1091,Table5[[#This Row],[SKU]],Demand_Data!H12:H1091) -> 3728.4444 | C12: {=STDEV(IF(Demand_Data!B12:B1091=Table5[[#This Row],[SKU]],Demand_Data!H12:H1091))} -> 601.26273 | D12: =Table5[[#This Row],[StDev Demand]]/Table5[[#This Row],[Mean Demand]] -> 0.1612637 | E12: =AVERAGEIFS(Purchase_Orders!I12:I71,Purchase_Orders!B12:B71,Table5[[#This Row],[SKU]]) -> 2240.5 | F12: {=STDEV(IF(Purchase_Orders!B12:B71=Table5[[#This Row],[SKU]],Purchase_Orders!I12:I71))} -> 382.90164 | G12: =Table5[[#This Row],[ StDev Orders]]/Table5[[#This Row],[ Mean Orders ]] -> 0.17090009 | H12: =Table5[[#This Row],[CV Orders]]/Table5[[#This Row],[ CV Demand ]] -> 1.0597555 | I12: =IF(Table5[[#This Row],[Bullwhip Ratio]]>1.5,"High Bullwhip",IF(Table5[[#This Row],[Bullwhip Ratio]]>1,"Moderate Bullwhip","Stable")) -> Moderate Bullwhip
A13: =Table2[[#This Row],[SKU_ID]] -> SKU012 | B13: =AVERAGEIF(Demand_Data!B13:B1092,Table5[[#This Row],[SKU]],Demand_Data!H13:H1092) -> 1447.8611 | C13: {=STDEV(IF(Demand_Data!B13:B1092=Table5[[#This Row],[SKU]],Demand_Data!H13:H1092))} -> 228.54206 | D13: =Table5[[#This Row],[StDev Demand]]/Table5[[#This Row],[Mean Demand]] -> 0.15784806 | E13: =AVERAGEIFS(Purchase_Orders!I13:I72,Purchase_Orders!B13:B72,Table5[[#This Row],[SKU]]) -> 859.25 | F13: {=STDEV(IF(Purchase_Orders!B13:B72=Table5[[#This Row],[SKU]],Purchase_Orders!I13:I72))} -> 187.54977 | G13: =Table5[[#This Row],[ StDev Orders]]/Table5[[#This Row],[ Mean Orders ]] -> 0.21827148 | H13: =Table5[[#This Row],[CV Orders]]/Table5[[#This Row],[ CV Demand ]] -> 1.3827949 | I13: =IF(Table5[[#This Row],[Bullwhip Ratio]]>1.5,"High Bullwhip",IF(Table5[[#This Row],[Bullwhip Ratio]]>1,"Moderate Bullwhip","Stable")) -> Moderate Bullwhip
... A16: =Table2[[#This Row],[SKU_ID]] -> SKU015 | B16: =AVERAGEIF(Demand_Data!B16:B1095,Table5[[#This Row],[SKU]],Demand_Data!H16:H1095) -> 770.06944 | C16: {=STDEV(IF(Demand_Data!B16:B1095=Table5[[#This Row],[SKU]],Demand_Data!H16:H1095))} -> 115.85571 | D16: =Table5[[#This Row],[StDev Demand]]/Table5[[#This Row],[Mean Demand]] -> 0.15044839 | E16: =AVERAGEIFS(Purchase_Orders!I16:I75,Purchase_Orders!B16:B75,Table5[[#This Row],[SKU]]) -> 455.5 | F16: {=STDEV(IF(Purchase_Orders!B16:B75=Table5[[#This Row],[SKU]],Purchase_Orders!I16:I75))} -> 71.355915 | G16: =Table5[[#This Row],[ StDev Orders]]/Table5[[#This Row],[ Mean Orders ]] -> 0.15665404 | H16: =Table5[[#This Row],[CV Orders]]/Table5[[#This Row],[ CV Demand ]] -> 1.0412477 | I16: =IF(Table5[[#This Row],[Bullwhip Ratio]]>1.5,"High Bullwhip",IF(Table5[[#This Row],[Bullwhip Ratio]]>1,"Moderate Bullwhip","Stable")) -> Moderate Bullwhip

Sheet  S&OP summary
A1: SKU | B1: Product | C1: Current Stock | D1: Incoming PO | E1: Total Supply | F1: 6M Forecast | G1: Gap | H1: Gap % | I1: Status
A2: =Table2[[#This Row],[SKU_ID]] -> SKU001 | B2: =Table2[[#This Row],[Product_Name]] -> Surf Excel 1kg | C2: =SUMIF(Table3[SKU_ID],Table6[[#This Row],[SKU]],Table3[Closing_Stock]) -> 9728 | D2: =SUMIF(Purchase_Orders!B2:B61,Table6[[#This Row],[SKU]],Purchase_Orders!I2:I61) -> 10682 | E2: =Table6[[#This Row],[Current Stock]]+Table6[[#This Row],[Incoming PO]] -> 20410 | F2: =SUMIF(Table1[Product],Table6[[#This Row],[Product]],Table1[Total forecast]) -> 87262.833 | G2: =Table6[[#This Row],[Total Supply]]-Table6[[#This Row],[6M Forecast]] -> -66852.833 | H2: =(Table6[[#This Row],[Gap]]/Table6[[#This Row],[6M Forecast]])*100 -> -76.61089 | I2: =IF(Table6[[#This Row],[Gap]]>0,"surplus",IF(Table6[[#This Row],[Gap]]<0,"shortage","ok")) -> shortage
A3: =Table2[[#This Row],[SKU_ID]] -> SKU002 | B3: =Table2[[#This Row],[Product_Name]] -> Surf Excel 500g | C3: =SUMIF(Table3[SKU_ID],Table6[[#This Row],[SKU]],Table3[Closing_Stock]) -> 17587 | D3: =SUMIF(Purchase_Orders!B3:B62,Table6[[#This Row],[SKU]],Purchase_Orders!I3:I62) -> 15611 | E3: =Table6[[#This Row],[Current Stock]]+Table6[[#This Row],[Incoming PO]] -> 33198 | F3: =SUMIF(Table1[Product],Table6[[#This Row],[Product]],Table1[Total forecast]) -> 148302.87 | G3: =Table6[[#This Row],[Total Supply]]-Table6[[#This Row],[6M Forecast]] -> -115104.87 | H3: =(Table6[[#This Row],[Gap]]/Table6[[#This Row],[6M Forecast]])*100 -> -77.614728 | I3: =IF(Table6[[#This Row],[Gap]]>0,"surplus",IF(Table6[[#This Row],[Gap]]<0,"shortage","ok")) -> shortage
A4: =Table2[[#This Row],[SKU_ID]] -> SKU003 | B4: =Table2[[#This Row],[Product_Name]] -> Vim Bar 200g | C4: =SUMIF(Table3[SKU_ID],Table6[[#This Row],[SKU]],Table3[Closing_Stock]) -> 25609 | D4: =SUMIF(Purchase_Orders!B4:B63,Table6[[#This Row],[SKU]],Purchase_Orders!I4:I63) -> 23371 | E4: =Table6[[#This Row],[Current Stock]]+Table6[[#This Row],[Incoming PO]] -> 48980 | F4: =SUMIF(Table1[Product],Table6[[#This Row],[Product]],Table1[Total forecast]) -> 201836.48 | G4: =Table6[[#This Row],[Total Supply]]-Table6[[#This Row],[6M Forecast]] -> -152856.48 | H4: =(Table6[[#This Row],[Gap]]/Table6[[#This Row],[6M Forecast]])*100 -> -75.732831 | I4: =IF(Table6[[#This Row],[Gap]]>0,"surplus",IF(Table6[[#This Row],[Gap]]<0,"shortage","ok")) -> shortage
A5: =Table2[[#This Row],[SKU_ID]] -> SKU004 | B5: =Table2[[#This Row],[Product_Name]] -> Vim Liquid 500ml | C5: =SUMIF(Table3[SKU_ID],Table6[[#This Row],[SKU]],Table3[Closing_Stock]) -> 6926 | D5: =SUMIF(Purchase_Orders!B5:B64,Table6[[#This Row],[SKU]],Purchase_Orders!I5:I64) -> 7980 | E5: =Table6[[#This Row],[Current Stock]]+Table6[[#This Row],[Incoming PO]] -> 14906 | F5: =SUMIF(Table1[Product],Table6[[#This Row],[Product]],Table1[Total forecast]) -> 66048.073 | G5: =Table6[[#This Row],[Total Supply]]-Table6[[#This Row],[6M Forecast]] -> -51142.073 | H5: =(Table6[[#This Row],[Gap]]/Table6[[#This Row],[6M Forecast]])*100 -> -77.43159 | I5: =IF(Table6[[#This Row],[Gap]]>0,"surplus",IF(Table6[[#This Row],[Gap]]<0,"shortage","ok")) -> shortage
A6: =Table2[[#This Row],[SKU_ID]] -> SKU005 | B6: =Table2[[#This Row],[Product_Name]] -> Lux Soap 100g | C6: =SUMIF(Table3[SKU_ID],Table6[[#This Row],[SKU]],Table3[Closing_Stock]) -> 43015 | D6: =SUMIF(Purchase_Orders!B6:B65,Table6[[#This Row],[SKU]],Purchase_Orders!I6:I65) -> 29409 | E6: =Table6[[#This Row],[Current Stock]]+Table6[[#This Row],[Incoming PO]] -> 72424 | F6: =SUMIF(Table1[Product],Table6[[#This Row],[Product]],Table1[Total forecast]) -> 246075.33 | G6: =Table6[[#This Row],[Total Supply]]-Table6[[#This Row],[6M Forecast]] -> -173651.33 | H6: =(Table6[[#This Row],[Gap]]/Table6[[#This Row],[6M Forecast]])*100 -> -70.568363 | I6: =IF(Table6[[#This Row],[Gap]]>0,"surplus",IF(Table6[[#This Row],[Gap]]<0,"shortage","ok")) -> shortage
A7: =Table2[[#This Row],[SKU_ID]] -> SKU006 | B7: =Table2[[#This Row],[Product_Name]] -> Lifebuoy 125g | C7: =SUMIF(Table3[SKU_ID],Table6[[#This Row],[SKU]],Table3[Closing_Stock]) -> 25833 | D7: =SUMIF(Purchase_Orders!B7:B66,Table6[[#This Row],[SKU]],Purchase_Orders!I7:I66) -> 23121 | E7: =Table6[[#This Row],[Current Stock]]+Table6[[#This Row],[Incoming PO]] -> 48954 | F7: =SUMIF(Table1[Product],Table6[[#This Row],[Product]],Table1[Total forecast]) -> 236744.92 | G7: =Table6[[#This Row],[Total Supply]]-Table6[[#This Row],[6M Forecast]] -> -187790.92 | H7: =(Table6[[#This Row],[Gap]]/Table6[[#This Row],[6M Forecast]])*100 -> -79.322048 | I7: =IF(Table6[[#This Row],[Gap]]>0,"surplus",IF(Table6[[#This Row],[Gap]]<0,"shortage","ok")) -> shortage
A8: =Table2[[#This Row],[SKU_ID]] -> SKU007 | B8: =Table2[[#This Row],[Product_Name]] -> Dove Shampoo 180ml | C8: =SUMIF(Table3[SKU_ID],Table6[[#This Row],[SKU]],Table3[Closing_Stock]) -> 5183 | D8: =SUMIF(Purchase_Orders!B8:B67,Table6[[#This Row],[SKU]],Purchase_Orders!I8:I67) -> 5359 | E8: =Table6[[#This Row],[Current Stock]]+Table6[[#This Row],[Incoming PO]] -> 10542 | F8: =SUMIF(Table1[Product],Table6[[#This Row],[Product]],Table1[Total forecast]) -> 37092.498 | G8: =Table6[[#This Row],[Total Supply]]-Table6[[#This Row],[6M Forecast]] -> -26550.498 | H8: =(Table6[[#This Row],[Gap]]/Table6[[#This Row],[6M Forecast]])*100 -> -71.579159 | I8: =IF(Table6[[#This Row],[Gap]]>0,"surplus",IF(Table6[[#This Row],[Gap]]<0,"shortage","ok")) -> shortage
A9: =Table2[[#This Row],[SKU_ID]] -> SKU008 | B9: =Table2[[#This Row],[Product_Name]] -> Sunsilk Shampoo 180ml | C9: =SUMIF(Table3[SKU_ID],Table6[[#This Row],[SKU]],Table3[Closing_Stock]) -> 5774 | D9: =SUMIF(Purchase_Orders!B9:B68,Table6[[#This Row],[SKU]],Purchase_Orders!I9:I68) -> 5245 | E9: =Table6[[#This Row],[Current Stock]]+Table6[[#This Row],[Incoming PO]] -> 11019 | F9: =SUMIF(Table1[Product],Table6[[#This Row],[Product]],Table1[Total forecast]) -> 45356.391 | G9: =Table6[[#This Row],[Total Supply]]-Table6[[#This Row],[6M Forecast]] -> -34337.391 | H9: =(Table6[[#This Row],[Gap]]/Table6[[#This Row],[6M Forecast]])*100 -> -75.705739 | I9: =IF(Table6[[#This Row],[Gap]]>0,"surplus",IF(Table6[[#This Row],[Gap]]<0,"shortage","ok")) -> shortage
A10: =Table2[[#This Row],[SKU_ID]] -> SKU009 | B10: =Table2[[#This Row],[Product_Name]] -> Vaseline 100ml | C10: =SUMIF(Table3[SKU_ID],Table6[[#This Row],[SKU]],Table3[Closing_Stock]) -> 4156 | D10: =SUMIF(Purchase_Orders!B10:B69,Table6[[#This Row],[SKU]],Purchase_Orders!I10:I69) -> 6161 | E10: =Table6[[#This Row],[Current Stock]]+Table6[[#This Row],[Incoming PO]] -> 10317 | F10: =SUMIF(Table1[Product],Table6[[#This Row],[Product]],Table1[Total forecast]) -> 58658.302 | G10: =Table6[[#This Row],[Total Supply]]-Table6[[#This Row],[6M Forecast]] -> -48341.302 | H10: =(Table6[[#This Row],[Gap]]/Table6[[#This Row],[6M Forecast]])*100 -> -82.411697 | I10: =IF(Table6[[#This Row],[Gap]]>0,"surplus",IF(Table6[[#This Row],[Gap]]<0,"shortage","ok")) -> shortage
A11: =Table2[[#This Row],[SKU_ID]] -> SKU010 | B11: =Table2[[#This Row],[Product_Name]] -> Clinic Plus 80ml | C11: =SUMIF(Table3[SKU_ID],Table6[[#This Row],[SKU]],Table3[Closing_Stock]) -> 10375 | D11: =SUMIF(Purchase_Orders!B11:B70,Table6[[#This Row],[SKU]],Purchase_Orders!I11:I70) -> 8173 | E11: =Table6[[#This Row],[Current Stock]]+Table6[[#This Row],[Incoming PO]] -> 18548 | F11: =SUMIF(Table1[Product],Table6[[#This Row],[Product]],Table1[Total forecast]) -> 75995.96 | G11: =Table6[[#This Row],[Total Supply]]-Table6[[#This Row],[6M Forecast]] -> -57447.96 | H11: =(Table6[[#This Row],[Gap]]/Table6[[#This Row],[6M Forecast]])*100 -> -75.59344 | I11: =IF(Table6[[#This Row],[Gap]]>0,"surplus",IF(Table6[[#This Row],[Gap]]<0,"shortage","ok")) -> shortage
A12: =Table2[[#This Row],[SKU_ID]] -> SKU011 | B12: =Table2[[#This Row],[Product_Name]] -> Rin Powder 1kg | C12: =SUMIF(Table3[SKU_ID],Table6[[#This Row],[SKU]],Table3[Closing_Stock]) -> 12314 | D12: =SUMIF(Purchase_Orders!B12:B71,Table6[[#This Row],[SKU]],Purchase_Orders!I12:I71) -> 8962 | E12: =Table6[[#This Row],[Current Stock]]+Table6[[#This Row],[Incoming PO]] -> 21276 | F12: =SUMIF(Table1[Product],Table6[[#This Row],[Product]],Table1[Total forecast]) -> 80929.322 | G12: =Table6[[#This Row],[Total Supply]]-Table6[[#This Row],[6M Forecast]] -> -59653.322 | H12: =(Table6[[#This Row],[Gap]]/Table6[[#This Row],[6M Forecast]])*100 -> -73.710394 | I12: =IF(Table6[[#This Row],[Gap]]>0,"surplus",IF(Table6[[#This Row],[Gap]]<0,"shortage","ok")) -> shortage
A13: =Table2[[#This Row],[SKU_ID]] -> SKU012 | B13: =Table2[[#This Row],[Product_Name]] -> Comfort 200ml | C13: =SUMIF(Table3[SKU_ID],Table6[[#This Row],[SKU]],Table3[Closing_Stock]) -> 4396 | D13: =SUMIF(Purchase_Orders!B13:B72,Table6[[#This Row],[SKU]],Purchase_Orders!I13:I72) -> 3437 | E13: =Table6[[#This Row],[Current Stock]]+Table6[[#This Row],[Incoming PO]] -> 7833 | F13: =SUMIF(Table1[Product],Table6[[#This Row],[Product]],Table1[Total forecast]) -> 29866.572 | G13: =Table6[[#This Row],[Total Supply]]-Table6[[#This Row],[6M Forecast]] -> -22033.572 | H13: =(Table6[[#This Row],[Gap]]/Table6[[#This Row],[6M Forecast]])*100 -> -73.773354 | I13: =IF(Table6[[#This Row],[Gap]]>0,"surplus",IF(Table6[[#This Row],[Gap]]<0,"shortage","ok")) -> shortage
... A16: =Table2[[#This Row],[SKU_ID]] -> SKU015 | B16: =Table2[[#This Row],[Product_Name]] -> Kissan Ketchup 500g | C16: =SUMIF(Table3[SKU_ID],Table6[[#This Row],[SKU]],Table3[Closing_Stock]) -> 2602 | D16: =SUMIF(Purchase_Orders!B16:B75,Table6[[#This Row],[SKU]],Purchase_Orders!I16:I75) -> 1822 | E16: =Table6[[#This Row],[Current Stock]]+Table6[[#This Row],[Incoming PO]] -> 4424 | F16: =SUMIF(Table1[Product],Table6[[#This Row],[Product]],Table1[Total forecast]) -> 15981.477 | G16: =Table6[[#This Row],[Total Supply]]-Table6[[#This Row],[6M Forecast]] -> -11557.477 | H16: =(Table6[[#This Row],[Gap]]/Table6[[#This Row],[6M Forecast]])*100 -> -72.317953 | I16: =IF(Table6[[#This Row],[Gap]]>0,"surplus",IF(Table6[[#This Row],[Gap]]<0,"shortage","ok")) -> shortage
